Workbook
Name corrected_dates: 'Transactions (Cleaned)'!$A$1:$K$10178

Sheet Transactions Overview
A1: transaction_id | B1: transaction_date | C1: account_type | D1: branch_city | E1: branch_state | F1: amount | G1: transaction_type | H1: category | I1: merchant | J1: payment_method | K1: status
A2: 106499 | B2: 45992 | C2: Money Market | D2: Albany | E2: NY | F2: -2282.09 | G2: Payment | H2: transportation | I2: EZ-Pass | J2: WIRE | K2: Completed
A3: 101635 | B3: 45715 | C3: savings | D3: Philadelphia | E3: Pennsylvania | F3: 431.86 | G3: Transfer | H3: transportation | I3: Lyft | K3: Pending
A4: 102938 | B4: 45443 | C4: Checking | D4: Stamford | E4: Connecticut | F4: 277.69 | G4: Transfer | H4: Shopping | I4: Amazon | J4: cash | K4: Completed
A5: 102938 | B5: 45443 | C5: Checking | D5: Stamford | E5: Connecticut | F5: 277.69 | G5: Transfer | H5: Shopping | I5: Amazon | J5: cash | K5: Completed
A6: 110478 | B6: 44762 | C6: credit card | D6: New York | E6: New York | F6: 2999.37 | G6: Transfer | H6: SHOPPING | I6: Target | J6: cash | K6: Completed
A7: 100906 | B7: 45254 | C7: savings | D7: Hartford | E7: CT | F7: -1087.05 | G7: Withdrawal | H7: fees | I7: Late Fee | J7: CASH | K7: Completed
A8: 104027 | B8: 45903 | C8: money market | D8: Jersey City | E8: New Jersey | F8: -102.75 | G8: Withdrawal | H8: Utility | I8: PSEG | J8: debit card | K8: Pending
A9: 105516 | B9: 45794 | C9: Credit Card | D9: New York | E9: NY | F9: -1605.73 | G9: Fee | H9: Rent | I9: Rent Payment | J9: cash | K9: Completed
A10: 108794 | B10: 45906 | C10: credit card | D10: Newark | E10: New Jersey | F10: 486.99 | G10: Deposit | H10: FEES | I10: Late Fee | J10: debit card | K10: Completed
A11: 107911 | B11: 44687 | C11: CHECKING | D11: Philadelphia | E11: Pennsylvania | F11: -1844.79 | G11: Payment | H11: Fee | I11: Late Fee | J11: CASH | K11: Completed
A12: 105279 | B12: 45774 | C12: money market | D12: Hicksville | E12: New York | F12: -2495.04 | G12: Withdrawal | H12: utilities | I12: National Grid | J12: Cash | K12: Completed
A13: 108373 | B13: 45968 | C13: Credit Card | D13: Boston | E13: MA | F13: 3060.68 | G13: Deposit | H13: Groceries | I13: Stop & Shop | J13: wire | K13: Completed
A14: 102618 | B14: 45346 | C14: Credit_Card | D14: Trenton | E14: New Jersey | F14: 2562.89 | G14: Transfer | H14: entertainment | I14: Hulu | J14: Cash | K14: Completed
A15: 102618 | B15: 45346 | C15: Credit_Card | D15: Trenton | E15: New Jersey | F15: 2562.89 | G15: Transfer | H15: entertainment | I15: Hulu | J15: Cash | K15: Completed
... A24: 107600 | B24: 45211 | C24: Money Market | D24: Albany | E24: New York | F24: 1954.44 | G24: Deposit | H24: Dining | I24: Starbucks | J24: Check | K24: Completed
A25: 100828 | B25: 24/04/2022 | C25: SAVINGS | D25: New York | E25: NY | F25: -1624.61 | G25: Fee | H25: Fee | I25: Late Fee | J25: ACH | K25: Completed
A26: 102560 | B26: 46230 | C26: money market | D26: BROOKLYN | E26: NY | F26: -430.51 | G26: Payment | H26: dining | I26: Starbucks | J26: CHECK | K26: Completed
A27: 102686 | B27: 45468 | C27: money market | D27: Jersey City | E27: NJ | F27: -842.49 | G27: Payment | H27: ENTERTAINMENT | I27: Hulu | J27: Check | K27: Completed
A28: 100504 | B28: 46056 | C28: Checking | D28: Boston | E28: Massachusetts | F28: -1531.07 | G28: Fee | H28: SHOPPING | I28: Best Buy | J28: Debit Card | K28: Completed
A29: 104092 | B29: 45008 | C29: Checking | D29: Trenton | E29: NJ | F29: -647.3 | G29: Withdrawal | H29: Transportation | I29: Shell Gas Station | J29: ach | K29: Completed
A30: 106340 | B30: 45341 | C30: money market | D30: Trenton | E30: New Jersey | F30: 118.5 | G30: Deposit | H30: Dining | I30: Chipotle | J30: credit card | K30: Completed
A31: 106340 | B31: 45341 | C31: money market | D31: Trenton | E31: New Jersey | F31: 118.5 | G31: Deposit | H31: Dining | I31: Chipotle | J31: credit card | K31: Completed
A32: 105305 | B32: 45571 | C32: checking | D32: Boston | E32: Massachusetts | F32: -821.76 | G32: Payment | H32: Entertainment | I32: Steam | K32: Completed
A33: 108240 | B33: 46117 | C33: money market | D33: Philadelphia | E33: PA | F33: -1601.03 | G33: Payment | H33: entertainment | I33: Netflix | J33: Cheque | K33: Completed
A34: 100840 | B34: 44690 | C34: CREDIT CARD | D34: Trenton | E34: New Jersey | F34: -219.92 | G34: Withdrawal | H34: Dining | I34: Chipotle | J34: ACH | K34: Completed
A35: 100840 | B35: 44690 | C35: CREDIT CARD | D35: Trenton | E35: New Jersey | F35: -219.92 | G35: Withdrawal | H35: Dining | I35: Chipotle | J35: ACH | K35: Completed
A36: 108931 | B36: 45608 | C36: Savings | D36: Philadelphia | E36: PA | F36: -685.09 | G36: Payment | H36: Shopping | I36: Walmart | J36: wire | K36: Completed
A37: 101832 | B37: 44974 | C37: money market | D37: Albany | E37: NY | F37: -326.64 | G37: Withdrawal | H37: HEALTHCARE | I37: Walgreens | J37: ACH | K37: Pending
A38: 105588 | B38: 44671 | C38: CHECKING | D38: Albany | E38: NY | F38: -2788.39 | G38: Payment | H38: insurance | I38: State Farm | J38: ach | K38: Completed
A39: 101703 | B39: 45556 | C39: Credit_Card | D39: New York | E39: New York | F39: -2600.4 | G39: Payment | H39: shopping | I39: Target | J39: Debit | K39: Completed
A40: 102630 | B40: 44912 | C40: credit card | D40: Philadelphia | E40: Pennsylvania | F40: -2251.77 | G40: Fee | H40: Fee | I40: ATM Fee | J40: Credit Card | K40: Completed
A41: 108467 | B41: 44984 | C41: money market | D41: Albany | E41: NY | F41: -964.9 | G41: Withdrawal | H41: Healthcare | I41: Copay - Dr. Visit | J41: Wire Transfer | K41: Completed
A42: 107547 | B42: 46077 | C42: CREDIT CARD | D42: Trenton | E42: New Jersey | F42: -2840.57 | G42: Payment | H42: Transfer | I42: Zelle Transfer | J42: cash | K42: Completed
A43: 107547 | B43: 46077 | C43: CREDIT CARD | D43: Trenton | E43: New Jersey | F43: -2840.57 | G43: Payment | H43: Transfer | I43: Zelle Transfer | J43: cash | K43: Completed
A44: 100499 | B44: 46178 | C44: money market | D44: Albany | E44: NY | F44: -393.53 | G44: Payment | H44: insurance | I44: Geico | J44: WIRE | K44: Completed
... A52: 110053 | B52: 45964 | C52: Credit Card | D52: Philadelphia | E52: PA | F52: 2591.34 | G52: Deposit | H52: transfer | I52: Venmo | J52: CHECK | K52: Completed
A53: 105509 | B53: 21/04/2025 | C53: savings | D53: White Plains | E53: New York | F53: 1492.32 | G53: Deposit | H53: Entertainment | I53: Netflix | J53: debit card | K53: Completed
A54: 108451 | B54: 46123 | C54: Money Market | D54: Brooklyn | E54: New York | F54: 2817.36 | G54: Transfer | H54: UTILITIES | I54: Verizon Fios | J54: ach | K54: Pending
A55: 109805 | B55: 45867 | C55: MoneyMarket | D55: Albany | E55: NY | F55: 3055.5 | G55: Transfer | H55: Health Care | I55: Copay - Dr. Visit | J55: check | K55: Completed
A56: 103004 | B56: 45388 | C56: Savings | D56: New York | E56: New York | F56: 1219.92 | G56: Transfer | H56: HEALTHCARE | J56: Cash | K56: Completed
A57: 103330 | B57: 45860 | C57: SAVINGS | D57: Trenton | E57: New Jersey | F57: -2618.76 | G57: Fee | H57: fees | I57: ATM Fee | J57: CREDIT CARD | K57: Completed
A58: 101632 | B58: 45261 | C58: SAVINGS | D58: Newark | E58: New Jersey | F58: -2901.12 | G58: Payment | H58: Dining | I58: Local Diner | J58: cash | K58: Completed
A59: 102146 | B59: 45305 | C59: Checking | D59: Trenton | E59: NJ | F59: 3004.07 | G59: Deposit | H59: transfer | I59: Zelle Transfer | J59: Cash | K59: Completed
A60: 103451 | B60: 44657 | C60: Savings | D60: Albany | E60: New York | F60: -760.84 | G60: Withdrawal | H60: Health Care | J60: ACH | K60: Completed
A61: 106969 | B61: 45097 | C61: Credit Card | D61: Albany | E61: NY | F61: 883.46 | G61: Deposit | H61: insurance | I61: Geico | J61: Cheque | K61: Completed
A62: 108191 | B62: 45150 | C62: Money Market | D62: New York | E62: New York | F62: -2262.11 | G62: Payment | H62: Transfer | I62: Internal Transfer | J62: Wire | K62: Failed
A63: 106446 | B63: 30/08/2022 | C63: credit card | D63: Trenton | E63: NJ | F63: 2134.87 | G63: Transfer | H63: entertainment | I63: AMC Theatres | J63: ach | K63: Completed
A64: 102187 | B64: 44752 | C64: money market | D64: Hartford | E64: Connecticut | F64: 2268.98 | G64: Transfer | H64: Shopping | I64: Target | J64: WIRE | K64: Completed
A65: 100608 | B65: 14/02/2025 | C65: CREDIT CARD | D65: Boston | E65: Massachusetts | F65: -566.37 | G65: Withdrawal | H65: Utility | I65: PSEG | J65: cash | K65: Completed
A66: 106011 | B66: 45501 | C66: checking | D66: White Plains | E66: New York | F66: 408.3 | G66: Transfer | H66: transfer | I66: Venmo | J66: Debit | K66: Completed
A67: 104819 | B67: 45111 | C67: CREDIT CARD | D67: Boston | E67: Massachusetts | F67: -473.42 | G67: Payment | H67: SALARY | I67: Payroll Deposit | K67: Completed
A68: 104819 | B68: 45111 | C68: CREDIT CARD | D68: Boston | E68: Massachusetts | F68: -473.42 | G68: Payment | H68: SALARY | I68: Payroll Deposit | K68: Completed
A69: 103239 | B69: 45390 | C69: Credit_Card | D69: New York | E69: NY | F69: -2193.75 | G69: Fee | H69: UTILITIES | I69: Con Edison | J69: CASH | K69: Completed
A70: 105901 | B70: 45268 | C70: savings | D70: Newark | E70: NJ | F70: 999.18 | G70: Deposit | H70: entertainment | I70: Hulu | J70: Debit Card | K70: Completed
A71: 100770 | B71: 45064 | C71: CREDIT CARD | D71: Hartford | E71: CT | F71: 425.84 | G71: Deposit | H71: utilities | I71: Verizon Fios | J71: check | K71: Completed
A72: 100770 | B72: 45064 | C72: CREDIT CARD | D72: Hartford | E72: CT | F72: 425.84 | G72: Deposit | H72: utilities | I72: Verizon Fios | J72: check | K72: Completed
A73: 102479 | B73: 18/07/2026 | C73: savings | D73: Philadelphia | E73: PA | F73: -1306.87 | G73: Payment | H73: FEES | I73: Monthly Maintenance Fee | J73: credit card | K73: Completed
A74: 108864 | B74: 45749 | C74: SAVINGS | D74: Boston | E74: Massachusetts | F74: 2095.22 | G74: Transfer | H74: groceries | I74: Whole Foods | J74: ach | K74: Completed
A75: 102559 | B75: 46205 | C75: SAVINGS | D75: White Plains | E75: New York | F75: -1313.32 | G75: Payment | H75: insurance | I75: State Farm | J75: DEBIT CARD | K75: Completed
A76: 107141 | B76: 44853 | C76: SAVINGS | D76: Brooklyn | E76: NY | F76: 2691.73 | G76: Transfer | H76: Entertainmnt | I76: Spotify | J76: WIRE | K76: Completed
A77: 107030 | B77: 44741 | C77: Savings | D77: Newark | E77: New Jersey | F77: 1671.85 | G77: Deposit | I77: Late Fee | J77: CASH | K77: Completed
A78: 101540 | B78: 45568 | C78: Credit Card | D78: Boston | E78: MA | F78: -1233.42 | G78: Fee | H78: Transfers | I78: Zelle Transfer | J78: ach
A79: 109504 | B79: 45234 | C79: Money Market | D79: Trenton | E79: New Jersey | F79: 1547.09 | G79: Transfer | H79: Groceries | I79: Whole Foods | J79: ACH | K79: Completed
A80: 103706 | B80: 45815 | C80: CREDIT CARD | D80: Hicksville | E80: NY | F80: -215.96 | G80: Withdrawal | H80: Transport | I80: Shell Gas Station | J80: ach | K80: Completed
A81: 108776 | B81: 44770 | C81: money market | D81: Hartford | E81: Connecticut | F81: 1249.02 | G81: Transfer | H81: rent | I81: Rent Payment | J81: Cheque | K81: Completed
A82: 100688 | B82: 45129 | C82: money market | D82: Boston | E82: Massachusetts | F82: 1403.42 | G82: Transfer | H82: insurance | I82: Blue Cross Blue Shield | J82: Wire Transfer | K82: Completed
A83: 103084 | B83: 45980 | C83: Checking | D83: Newark | E83: NJ | F83: -2936.01 | G83: Payment | H83: healthcare | I83: Walgreens | J83: Cheque | K83: Pending
A84: 107850 | B84: 45985 | C84: CREDIT CARD | D84: Boston | E84: Massachusetts | F84: -209.7 | G84: Withdrawal | H84: salary | I84: Payroll Deposit | J84: CHECK | K84: Completed
A85: 103327 | B85: 45724 | C85: money market | D85: Jersey City | E85: NJ | F85: -1322.87 | G85: Withdrawal | H85: Healthcare | I85: Quest Diagnostics | J85: DEBIT CARD | K85: Completed
A86: 109368 | B86: 44702 | C86: Checking | D86: Stamford | E86: CT | F86: -1456.29 | G86: Withdrawal | H86: insurance | I86: Geico | J86: Credit Card | K86: Completed
A87: 110167 | B87: 45968 | C87: Savings | D87: Jersey City | E87: NJ | F87: -398.28 | G87: Payment | H87: Rent Payment | I87: Rent Payment | J87: debit card | K87: Completed
A88: 110167 | B88: 45968 | C88: Savings | D88: Jersey City | E88: NJ | F88: -398.28 | G88: Payment | H88: Rent Payment | I88: Rent Payment | J88: debit card | K88: Completed
A89: 101658 | B89: 44900 | C89: Money Market | D89: Trenton | E89: New Jersey | F89: 2661.14 | G89: Transfer | H89: insurance | I89: Blue Cross Blue Shield | J89: debit card | K89: Completed
A90: 107428 | B90: 44777 | C90: Savings | D90: Stamford | E90: Connecticut | F90: 2427.48 | G90: Transfer | H90: Utility | I90: Con Edison | K90: Completed
A91: 102802 | B91: 45623 | C91: Credit Card | D91: New York | E91: New York | F91: 2865.48 | G91: Transfer | H91: Insurance | I91: State Farm | J91: cash | K91: Completed
A92: 108937 | B92: 45398 | C92: savings | D92: Boston | E92: Massachusetts | F92: 272.38 | G92: Transfer | H92: Grocery | I92: Trader Joe's | J92: Wire Transfer | K92: Completed
A93: 109304 | B93: 45245 | C93: checking | D93: Brooklyn | E93: NY | F93: 1894.59 | G93: Deposit | H93: SALARY | I93: Payroll Deposit | J93: credit card | K93: Completed
A94: 107949 | B94: 13/07/2022 | C94: credit card | D94: Hartford | E94: CT | F94: 2476.37 | G94: Deposit | H94: Rent | I94: Rent Payment | J94: credit card | K94: Completed
A95: 107034 | B95: 29/04/2025 | C95: money market | D95: White Plains | E95: NY | F95: 1497.67 | G95: Deposit | H95: TRANSPORTATION | I95: EZ-Pass | J95: Debit Card | K95: Completed
A96: 100404 | B96: 46229 | C96: Savings | D96: Trenton | E96: NJ | F96: 1857.82 | G96: Transfer | H96: Transport | I96: MTA | J96: Wire | K96: Completed
A97: 107082 | B97: 44976 | C97: Savings | D97: Hicksville | E97: NY | F97: 2078.24 | G97: Transfer | H97: HEALTHCARE | I97: Quest Diagnostics | J97: check | K97: Completed
A98: 109681 | B98: 45938 | C98: Savings | D98: Jersey City | E98: NJ | F98: 2499.11 | G98: Deposit | H98: ENTERTAINMENT | I98: Spotify | J98: Wire Transfer | K98: Completed
A99: 109681 | B99: 45938 | C99: Savings | D99: Jersey City | E99: NJ | F99: 2499.11 | G99: Deposit | H99: ENTERTAINMENT | I99: Spotify | J99: Wire Transfer | K99: Completed
A100: 103780 | B100: 45788 | C100: savings | D100: Jersey City | E100: New Jersey | F100: -1224.72 | G100: Withdrawal | H100: Healthcare | I100: Walgreens | J100: check | K100: Completed
A101: 102487 | B101: 44947 | C101: Money Market | D101: Stamford | E101: CT | F101: 643.21 | G101: Deposit | H101: Dining | I101: DoorDash | J101: Wire Transfer | K101: Completed
A102: 105630 | B102: 44883 | C102: Credit Card | D102: Hartford | E102: CT | F102: -2447.6 | G102: Payment | H102: groceries | I102: Costco | J102: ach | K102: Completed
A103: 105630 | B103: 44883 | C103: Credit Card | D103: Hartford | E103: CT | F103: -2447.6 | G103: Payment | H103: groceries | I103: Costco | J103: ach | K103: Completed
A104: 102135 | B104: 44994 | C104: CREDIT CARD | D104: Trenton | E104: New Jersey | F104: 742.92 | G104: Deposit | I104: Payroll Deposit | J104: ACH | K104: Completed
A105: 102135 | B105: 44994 | C105: CREDIT CARD | D105: Trenton | E105: New Jersey | F105: 742.92 | G105: Deposit | I105: Payroll Deposit | J105: ACH | K105: Completed
A106: 103834 | B106: 45969 | C106: MoneyMarket | D106: Trenton | E106: NJ | F106: 1174.72 | G106: Transfer | H106: Transfers | I106: Internal Transfer | J106: Debit | K106: Completed
A107: 104783 | B107: 45780 | C107: SAVINGS | D107: Jersey City | E107: NJ | F107: 2301.89 | G107: Transfer | H107: UTILITIES | I107: National Grid | J107: CHECK | K107: Pending
A108: 102551 | B108: 45711 | C108: credit card | D108: Philadelphia | E108: PA | F108: -2382.48 | G108: Withdrawal | H108: shopping | I108: Amazon | J108: Credit | K108: Completed
A109: 100094 | B109: 44719 | C109: Credit Card | D109: New York | E109: NY | F109: 2236.31 | G109: Deposit | H109: transportation | I109: Uber | J109: check | K109: Completed
A110: 103104 | B110: 45722 | C110: Savings | D110: Stamford | E110: Connecticut | F110: 2184.55 | G110: Transfer | H110: ENTERTAINMENT | I110: Spotify | J110: credit card | K110: Completed
A111: 105850 | B111: 45728 | C111: SAVINGS | D111: White Plains | E111: New York | F111: -1104.76 | G111: Payment | H111: GROCERIES | I111: ShopRite | J111: CHECK | K111: Completed
A112: 101551 | B112: 46060 | C112: Money Market | D112: Philadelphia | E112: PA | F112: 887.02 | G112: Deposit | H112: utilities | I112: Verizon Fios | J112: CASH | K112: Completed
A113: 110424 | B113: 46212 | C113: credit card | D113: Boston | E113: MA | F113: 738.61 | G113: Transfer | H113: Transfer | I113: Internal Transfer | J113: wire | K113: Completed
A114: 103098 | B114: 45686 | C114: savings | D114: Philadelphia | E114: PA | F114: -663.53 | G114: Withdrawal | H114: SHOPPING | I114: Amazon | J114: check | K114: Completed
A115: 104316 | B115: 18/09/2025 | C115: Credit Card | D115: New York | E115: NY | F115: 1166.09 | G115: Transfer | H115: TRANSPORTATION | I115: Lyft | J115: check | K115: Completed
...

Sheet Transactions Overview (2)
A1: transaction_id | B1: transaction_date | C1: account_type | D1: branch_city | E1: branch_state | F1: amount | G1: transaction_type | H1: category | I1: merchant | J1: payment_method | K1: status
A2: 106499 | B2: 45992 | C2: =PROPER('Transactions Overview'!C2) -> Money Market | D2: =PROPER('Transactions Overview'!D2) -> Albany | E2: New York | F2: =ABS('Transactions Overview'!F2) -> 2282.09 | G2: Payment | H2: =PROPER('Transactions Overview'!H2) -> Transportation | I2: EZ-Pass | J2: Wire Transfer | K2: Completed
A3: 101635 | B3: 45715 | C3: =PROPER('Transactions Overview'!C3) -> Savings | D3: =PROPER('Transactions Overview'!D3) -> Philadelphia | E3: Pennsylvania | F3: =ABS('Transactions Overview'!F3) -> 431.86 | G3: Transfer | H3: =PROPER('Transactions Overview'!H3) -> Transportation | I3: Lyft | J3: =PROPER('Transactions Overview'!J3) | K3: Pending
A4: 102938 | B4: 45443 | C4: =PROPER('Transactions Overview'!C4) -> Checking | D4: =PROPER('Transactions Overview'!D4) -> Stamford | E4: Connecticut | F4: =ABS('Transactions Overview'!F4) -> 277.69 | G4: Transfer | H4: =PROPER('Transactions Overview'!H4) -> Shopping | I4: Amazon | J4: =PROPER('Transactions Overview'!J4) -> Cash | K4: Completed
A5: 110478 | B5: 44762 | C5: =PROPER('Transactions Overview'!C6) -> Credit Card | D5: =PROPER('Transactions Overview'!D6) -> New York | E5: New York | F5: =ABS('Transactions Overview'!F6) -> 2999.37 | G5: Transfer | H5: =PROPER('Transactions Overview'!H6) -> Shopping | I5: Target | J5: =PROPER('Transactions Overview'!J6) -> Cash | K5: Completed
A6: 100906 | B6: 45254 | C6: =PROPER('Transactions Overview'!C7) -> Savings | D6: =PROPER('Transactions Overview'!D7) -> Hartford | E6: Connecticut | F6: =ABS('Transactions Overview'!F7) -> 1087.05 | G6: Withdrawal | H6: =PROPER('Transactions Overview'!H7) -> Fees | I6: Late Fee | J6: =PROPER('Transactions Overview'!J7) -> Cash | K6: Completed
A7: 104027 | B7: 45903 | C7: =PROPER('Transactions Overview'!C8) -> Money Market | D7: =PROPER('Transactions Overview'!D8) -> Jersey City | E7: New Jersey | F7: =ABS('Transactions Overview'!F8) -> 102.75 | G7: Withdrawal | H7: Utilities | I7: PSEG | J7: =PROPER('Transactions Overview'!J8) -> Debit Card | K7: Pending
A8: 105516 | B8: 45794 | C8: =PROPER('Transactions Overview'!C9) -> Credit Card | D8: =PROPER('Transactions Overview'!D9) -> New York | E8: New York | F8: =ABS('Transactions Overview'!F9) -> 1605.73 | G8: Fee | H8: =PROPER('Transactions Overview'!H9) -> Rent | I8: Rent Payment | J8: =PROPER('Transactions Overview'!J9) -> Cash | K8: Completed
A9: 108794 | B9: 45906 | C9: =PROPER('Transactions Overview'!C10) -> Credit Card | D9: =PROPER('Transactions Overview'!D10) -> Newark | E9: New Jersey | F9: =ABS('Transactions Overview'!F10) -> 486.99 | G9: Deposit | H9: =PROPER('Transactions Overview'!H10) -> Fees | I9: Late Fee | J9: =PROPER('Transactions Overview'!J10) -> Debit Card | K9: Completed
A10: 107911 | B10: 44687 | C10: =PROPER('Transactions Overview'!C11) -> Checking | D10: =PROPER('Transactions Overview'!D11) -> Philadelphia | E10: Pennsylvania | F10: =ABS('Transactions Overview'!F11) -> 1844.79 | G10: Payment | H10: Fees | I10: Late Fee | J10: =PROPER('Transactions Overview'!J11) -> Cash | K10: Completed
A11: 105279 | B11: 45774 | C11: =PROPER('Transactions Overview'!C12) -> Money Market | D11: =PROPER('Transactions Overview'!D12) -> Hicksville | E11: New York | F11: =ABS('Transactions Overview'!F12) -> 2495.04 | G11: Withdrawal | H11: =PROPER('Transactions Overview'!H12) -> Utilities | I11: National Grid | J11: =PROPER('Transactions Overview'!J12) -> Cash | K11: Completed
A12: 108373 | B12: 45968 | C12: =PROPER('Transactions Overview'!C13) -> Credit Card | D12: =PROPER('Transactions Overview'!D13) -> Boston | E12: Massachusetts | F12: =ABS('Transactions Overview'!F13) -> 3060.68 | G12: Deposit | H12: =PROPER('Transactions Overview'!H13) -> Groceries | I12: Stop & Shop | J12: Wire Transfer | K12: Completed
A13: 102618 | B13: 45346 | C13: Credit Card | D13: =PROPER('Transactions Overview'!D14) -> Trenton | E13: New Jersey | F13: =ABS('Transactions Overview'!F14) -> 2562.89 | G13: Transfer | H13: =PROPER('Transactions Overview'!H14) -> Entertainment | I13: Hulu | J13: =PROPER('Transactions Overview'!J14) -> Cash | K13: Completed
A14: 105580 | B14: 45522 | C14: =PROPER('Transactions Overview'!C16) -> Checking | D14: =PROPER('Transactions Overview'!D16) -> Albany | E14: New York | F14: =ABS('Transactions Overview'!F16) -> 1344.25 | G14: Withdrawal | H14: =PROPER('Transactions Overview'!H16) -> Transportation | I14: EZ-Pass | J14: =PROPER('Transactions Overview'!J16) -> Check | K14: Completed
A15: 101092 | B15: 45096 | C15: =PROPER('Transactions Overview'!C17) -> Savings | D15: =PROPER('Transactions Overview'!D17) -> Trenton | E15: New Jersey | F15: =ABS('Transactions Overview'!F17) -> 133.77 | G15: Withdrawal | H15: =PROPER('Transactions Overview'!H17) -> Groceries | I15: Stop & Shop | J15: Wire Transfer | K15: Completed
A16: 104665 | B16: 45242 | C16: =PROPER('Transactions Overview'!C18) -> Checking | D16: =PROPER('Transactions Overview'!D18) -> Philadelphia | E16: Pennsylvania | F16: =ABS('Transactions Overview'!F18) -> 1958.72 | G16: Transfer | H16: =PROPER('Transactions Overview'!H18) -> Rent | I16: Rent Payment | J16: =PROPER('Transactions Overview'!J18) -> Cash | K16: Completed
A17: 104554 | B17: 46206 | C17: =PROPER('Transactions Overview'!C19) -> Credit Card | D17: =PROPER('Transactions Overview'!D19) -> Boston | E17: Massachusetts | F17: =ABS('Transactions Overview'!F19) -> 408.93 | G17: Payment | H17: Entertainment | I17: AMC Theatres | J17: =PROPER('Transactions Overview'!J19) -> Debit Card | K17: Completed
A18: 103646 | B18: 45608 | C18: =PROPER('Transactions Overview'!C20) -> Credit Card | D18: =PROPER('Transactions Overview'!D20) -> Philadelphia | E18: Pennsylvania | F18: =ABS('Transactions Overview'!F20) -> 1381.04 | G18: Withdrawal | H18: =PROPER('Transactions Overview'!H20) -> Groceries | I18: Costco | J18: =PROPER('Transactions Overview'!J20) -> Cash | K18: Completed
A19: 100837 | B19: 45166 | C19: Money Market | D19: =PROPER('Transactions Overview'!D21) -> Hartford | E19: Connecticut | F19: =ABS('Transactions Overview'!F21) -> 1783.21 | G19: Payment | H19: Income | I19: Payroll Deposit | J19: =PROPER('Transactions Overview'!J21) -> Debit Card | K19: Completed
A20: 105385 | B20: 44689 | C20: =PROPER('Transactions Overview'!C22) -> Credit Card | D20: =PROPER('Transactions Overview'!D22) -> Newark | E20: New Jersey | F20: =ABS('Transactions Overview'!F22) -> 2487.15 | G20: Transfer | H20: =PROPER('Transactions Overview'!H22) -> Transportation | I20: Uber | J20: Wire Transfer | K20: Pending
A21: 101831 | B21: 45582 | C21: =PROPER('Transactions Overview'!C23) -> Money Market | D21: =PROPER('Transactions Overview'!D23) -> Albany | E21: New York | F21: =ABS('Transactions Overview'!F23) -> 562.04 | G21: Deposit | H21: =PROPER('Transactions Overview'!H23) -> Groceries | I21: Whole Foods | J21: ACH | K21: Completed
A22: 107600 | B22: 45211 | C22: =PROPER('Transactions Overview'!C24) -> Money Market | D22: =PROPER('Transactions Overview'!D24) -> Albany | E22: New York | F22: =ABS('Transactions Overview'!F24) -> 1954.44 | G22: Deposit | H22: =PROPER('Transactions Overview'!H24) -> Dining | I22: Starbucks | J22: =PROPER('Transactions Overview'!J24) -> Check | K22: Completed
A23: 100828 | B23: 24/04/2022 | C23: =PROPER('Transactions Overview'!C25) -> Savings | D23: =PROPER('Transactions Overview'!D25) -> New York | E23: New York | F23: =ABS('Transactions Overview'!F25) -> 1624.61 | G23: Fee | H23: Fees | I23: Late Fee | J23: ACH | K23: Completed
A24: 102560 | B24: 46230 | C24: =PROPER('Transactions Overview'!C26) -> Money Market | D24: =PROPER('Transactions Overview'!D26) -> Brooklyn | E24: New York | F24: =ABS('Transactions Overview'!F26) -> 430.51 | G24: Payment | H24: =PROPER('Transactions Overview'!H26) -> Dining | I24: Starbucks | J24: =PROPER('Transactions Overview'!J26) -> Check | K24: Completed
A25: 102686 | B25: 45468 | C25: =PROPER('Transactions Overview'!C27) -> Money Market | D25: =PROPER('Transactions Overview'!D27) -> Jersey City | E25: New Jersey | F25: =ABS('Transactions Overview'!F27) -> 842.49 | G25: Payment | H25: =PROPER('Transactions Overview'!H27) -> Entertainment | I25: Hulu | J25: =PROPER('Transactions Overview'!J27) -> Check | K25: Completed
A26: 100504 | B26: 46056 | C26: =PROPER('Transactions Overview'!C28) -> Checking | D26: =PROPER('Transactions Overview'!D28) -> Boston | E26: Massachusetts | F26: =ABS('Transactions Overview'!F28) -> 1531.07 | G26: Fee | H26: =PROPER('Transactions Overview'!H28) -> Shopping | I26: Best Buy | J26: =PROPER('Transactions Overview'!J28) -> Debit Card | K26: Completed
A27: 104092 | B27: 45008 | C27: =PROPER('Transactions Overview'!C29) -> Checking | D27: =PROPER('Transactions Overview'!D29) -> Trenton | E27: New Jersey | F27: =ABS('Transactions Overview'!F29) -> 647.3 | G27: Withdrawal | H27: =PROPER('Transactions Overview'!H29) -> Transportation | I27: Shell Gas Station | J27: ACH | K27: Completed
A28: 106340 | B28: 45341 | C28: =PROPER('Transactions Overview'!C30) -> Money Market | D28: =PROPER('Transactions Overview'!D30) -> Trenton | E28: New Jersey | F28: =ABS('Transactions Overview'!F30) -> 118.5 | G28: Deposit | H28: =PROPER('Transactions Overview'!H30) -> Dining | I28: Chipotle | J28: =PROPER('Transactions Overview'!J30) -> Credit Card | K28: Completed
A29: 105305 | B29: 45571 | C29: =PROPER('Transactions Overview'!C32) -> Checking | D29: =PROPER('Transactions Overview'!D32) -> Boston | E29: Massachusetts | F29: =ABS('Transactions Overview'!F32) -> 821.76 | G29: Payment | H29: =PROPER('Transactions Overview'!H32) -> Entertainment | I29: Steam | J29: =PROPER('Transactions Overview'!J32) | K29: Completed
A30: 108240 | B30: 46117 | C30: =PROPER('Transactions Overview'!C33) -> Money Market | D30: =PROPER('Transactions Overview'!D33) -> Philadelphia | E30: Pennsylvania | F30: =ABS('Transactions Overview'!F33) -> 1601.03 | G30: Payment | H30: =PROPER('Transactions Overview'!H33) -> Entertainment | I30: Netflix | J30: Check | K30: Completed
A31: 100840 | B31: 44690 | C31: =PROPER('Transactions Overview'!C34) -> Credit Card | D31: =PROPER('Transactions Overview'!D34) -> Trenton | E31: New Jersey | F31: =ABS('Transactions Overview'!F34) -> 219.92 | G31: Withdrawal | H31: =PROPER('Transactions Overview'!H34) -> Dining | I31: Chipotle | J31: ACH | K31: Completed
A32: 108931 | B32: 45608 | C32: =PROPER('Transactions Overview'!C36) -> Savings | D32: =PROPER('Transactions Overview'!D36) -> Philadelphia | E32: Pennsylvania | F32: =ABS('Transactions Overview'!F36) -> 685.09 | G32: Payment | H32: =PROPER('Transactions Overview'!H36) -> Shopping | I32: Walmart | J32: Wire Transfer | K32: Completed
A33: 101832 | B33: 44974 | C33: =PROPER('Transactions Overview'!C37) -> Money Market | D33: =PROPER('Transactions Overview'!D37) -> Albany | E33: New York | F33: =ABS('Transactions Overview'!F37) -> 326.64 | G33: Withdrawal | H33: =PROPER('Transactions Overview'!H37) -> Healthcare | I33: Walgreens | J33: ACH | K33: Pending
A34: 105588 | B34: 44671 | C34: =PROPER('Transactions Overview'!C38) -> Checking | D34: =PROPER('Transactions Overview'!D38) -> Albany | E34: New York | F34: =ABS('Transactions Overview'!F38) -> 2788.39 | G34: Payment | H34: =PROPER('Transactions Overview'!H38) -> Insurance | I34: State Farm | J34: ACH | K34: Completed
A35: 101703 | B35: 45556 | C35: Credit Card | D35: =PROPER('Transactions Overview'!D39) -> New York | E35: New York | F35: =ABS('Transactions Overview'!F39) -> 2600.4 | G35: Payment | H35: =PROPER('Transactions Overview'!H39) -> Shopping | I35: Target | J35: Debit Card | K35: Completed
A36: 102630 | B36: 44912 | C36: =PROPER('Transactions Overview'!C40) -> Credit Card | D36: =PROPER('Transactions Overview'!D40) -> Philadelphia | E36: Pennsylvania | F36: =ABS('Transactions Overview'!F40) -> 2251.77 | G36: Fee | H36: Fees | I36: ATM Fee | J36: =PROPER('Transactions Overview'!J40) -> Credit Card | K36: Completed
A37: 108467 | B37: 44984 | C37: =PROPER('Transactions Overview'!C41) -> Money Market | D37: =PROPER('Transactions Overview'!D41) -> Albany | E37: New York | F37: =ABS('Transactions Overview'!F41) -> 964.9 | G37: Withdrawal | H37: =PROPER('Transactions Overview'!H41) -> Healthcare | I37: Copay - Dr. Visit | J37: =PROPER('Transactions Overview'!J41) -> Wire Transfer | K37: Completed
A38: 107547 | B38: 46077 | C38: =PROPER('Transactions Overview'!C42) -> Credit Card | D38: =PROPER('Transactions Overview'!D42) -> Trenton | E38: New Jersey | F38: =ABS('Transactions Overview'!F42) -> 2840.57 | G38: Payment | H38: Transfers | I38: Zelle Transfer | J38: =PROPER('Transactions Overview'!J42) -> Cash | K38: Completed
A39: 100499 | B39: 46178 | C39: =PROPER('Transactions Overview'!C44) -> Money Market | D39: =PROPER('Transactions Overview'!D44) -> Albany | E39: New York | F39: =ABS('Transactions Overview'!F44) -> 393.53 | G39: Payment | H39: =PROPER('Transactions Overview'!H44) -> Insurance | I39: Geico | J39: Wire Transfer | K39: Completed
A40: 102987 | B40: 45826 | C40: =PROPER('Transactions Overview'!C45) -> Money Market | D40: =PROPER('Transactions Overview'!D45) -> Stamford | E40: Connecticut | F40: =ABS('Transactions Overview'!F45) -> 2529.06 | G40: Deposit | H40: =PROPER('Transactions Overview'!H45) -> Groceries | I40: Trader Joe's | J40: ACH | K40: Completed
A41: 101550 | B41: 46254 | C41: =PROPER('Transactions Overview'!C46) -> Checking | D41: =PROPER('Transactions Overview'!D46) -> Philadelphia | E41: Pennsylvania | F41: =ABS('Transactions Overview'!F46) -> 303.04 | G41: Withdrawal | H41: =PROPER('Transactions Overview'!H46) -> Shopping | I41: Best Buy | J41: =PROPER('Transactions Overview'!J46) -> Cash | K41: Completed
A42: 106086 | B42: 44895 | C42: Credit Card | D42: =PROPER('Transactions Overview'!D47) -> Brooklyn | E42: New York | F42: =ABS('Transactions Overview'!F47) -> 3176.65 | G42: Withdrawal | H42: Utilities | I42: Con Edison | J42: Debit Card | K42: Completed
A43: 104231 | B43: 45673 | C43: =PROPER('Transactions Overview'!C48) -> Savings | D43: =PROPER('Transactions Overview'!D48) -> Hartford | E43: Connecticut | F43: =ABS('Transactions Overview'!F48) -> 1830.82 | G43: Payment | H43: =PROPER('Transactions Overview'!H48) -> Salary | I43: Payroll Deposit | J43: =PROPER('Transactions Overview'!J48) -> Check | K43: Completed
A44: 104254 | B44: 44763 | C44: =PROPER('Transactions Overview'!C49) -> Checking | D44: =PROPER('Transactions Overview'!D49) -> Newark | E44: New Jersey | F44: =ABS('Transactions Overview'!F49) -> 885.49 | G44: Withdrawal | H44: =PROPER('Transactions Overview'!H49) -> Healthcare | I44: CVS Pharmacy | J44: =PROPER('Transactions Overview'!J49) -> Cash | K44: Completed
A45: 108948 | B45: 45456 | C45: =PROPER('Transactions Overview'!C50) -> Savings | D45: =PROPER('Transactions Overview'!D50) -> Boston | E45: Massachusetts | F45: =ABS('Transactions Overview'!F50) -> 1878.02 | G45: Withdrawal | H45: =PROPER('Transactions Overview'!H50) -> Fees | I45: ATM Fee | J45: Check | K45: Completed
A46: 110053 | B46: 45964 | C46: =PROPER('Transactions Overview'!C52) -> Credit Card | D46: =PROPER('Transactions Overview'!D52) -> Philadelphia | E46: Pennsylvania | F46: =ABS('Transactions Overview'!F52) -> 2591.34 | G46: Deposit | H46: Transfers | I46: Venmo | J46: =PROPER('Transactions Overview'!J52) -> Check | K46: Completed
A47: 105509 | B47: 21/04/2025 | C47: =PROPER('Transactions Overview'!C53) -> Savings | D47: =PROPER('Transactions Overview'!D53) -> White Plains | E47: New York | F47: =ABS('Transactions Overview'!F53) -> 1492.32 | G47: Deposit | H47: =PROPER('Transactions Overview'!H53) -> Entertainment | I47: Netflix | J47: =PROPER('Transactions Overview'!J53) -> Debit Card | K47: Completed
A48: 108451 | B48: 46123 | C48: =PROPER('Transactions Overview'!C54) -> Money Market | D48: =PROPER('Transactions Overview'!D54) -> Brooklyn | E48: New York | F48: =ABS('Transactions Overview'!F54) -> 2817.36 | G48: Transfer | H48: =PROPER('Transactions Overview'!H54) -> Utilities | I48: Verizon Fios | J48: ACH | K48: Pending
A49: 109805 | B49: 45867 | C49: Money Market | D49: =PROPER('Transactions Overview'!D55) -> Albany | E49: New York | F49: =ABS('Transactions Overview'!F55) -> 3055.5 | G49: Transfer | H49: Healthcare | I49: Copay - Dr. Visit | J49: =PROPER('Transactions Overview'!J55) -> Check | K49: Completed
A50: 103004 | B50: 45388 | C50: =PROPER('Transactions Overview'!C56) -> Savings | D50: =PROPER('Transactions Overview'!D56) -> New York | E50: New York | F50: =ABS('Transactions Overview'!F56) -> 1219.92 | G50: Transfer | H50: =PROPER('Transactions Overview'!H56) -> Healthcare | J50: =PROPER('Transactions Overview'!J56) -> Cash | K50: Completed
A51: 103330 | B51: 45860 | C51: =PROPER('Transactions Overview'!C57) -> Savings | D51: =PROPER('Transactions Overview'!D57) -> Trenton | E51: New Jersey | F51: =ABS('Transactions Overview'!F57) -> 2618.76 | G51: Fee | H51: =PROPER('Transactions Overview'!H57) -> Fees | I51: ATM Fee | J51: =PROPER('Transactions Overview'!J57) -> Credit Card | K51: Completed
A52: 101632 | B52: 45261 | C52: =PROPER('Transactions Overview'!C58) -> Savings | D52: =PROPER('Transactions Overview'!D58) -> Newark | E52: New Jersey | F52: =ABS('Transactions Overview'!F58) -> 2901.12 | G52: Payment | H52: =PROPER('Transactions Overview'!H58) -> Dining | I52: Local Diner | J52: =PROPER('Transactions Overview'!J58) -> Cash | K52: Completed
A53: 102146 | B53: 45305 | C53: =PROPER('Transactions Overview'!C59) -> Checking | D53: =PROPER('Transactions Overview'!D59) -> Trenton | E53: New Jersey | F53: =ABS('Transactions Overview'!F59) -> 3004.07 | G53: Deposit | H53: Transfers | I53: Zelle Transfer | J53: =PROPER('Transactions Overview'!J59) -> Cash | K53: Completed
A54: 103451 | B54: 44657 | C54: =PROPER('Transactions Overview'!C60) -> Savings | D54: =PROPER('Transactions Overview'!D60) -> Albany | E54: New York | F54: =ABS('Transactions Overview'!F60) -> 760.84 | G54: Withdrawal | H54: Healthcare | J54: ACH | K54: Completed
A55: 106969 | B55: 45097 | C55: =PROPER('Transactions Overview'!C61) -> Credit Card | D55: =PROPER('Transactions Overview'!D61) -> Albany | E55: New York | F55: =ABS('Transactions Overview'!F61) -> 883.46 | G55: Deposit | H55: =PROPER('Transactions Overview'!H61) -> Insurance | I55: Geico | J55: Check | K55: Completed
A56: 108191 | B56: 45150 | C56: =PROPER('Transactions Overview'!C62) -> Money Market | D56: =PROPER('Transactions Overview'!D62) -> New York | E56: New York | F56: =ABS('Transactions Overview'!F62) -> 2262.11 | G56: Payment | H56: Transfers | I56: Internal Transfer | J56: Wire Transfer | K56: Failed
A57: 106446 | B57: 30/08/2022 | C57: =PROPER('Transactions Overview'!C63) -> Credit Card | D57: =PROPER('Transactions Overview'!D63) -> Trenton | E57: New Jersey | F57: =ABS('Transactions Overview'!F63) -> 2134.87 | G57: Transfer | H57: =PROPER('Transactions Overview'!H63) -> Entertainment | I57: AMC Theatres | J57: ACH | K57: Completed
A58: 102187 | B58: 44752 | C58: =PROPER('Transactions Overview'!C64) -> Money Market | D58: =PROPER('Transactions Overview'!D64) -> Hartford | E58: Connecticut | F58: =ABS('Transactions Overview'!F64) -> 2268.98 | G58: Transfer | H58: =PROPER('Transactions Overview'!H64) -> Shopping | I58: Target | J58: Wire Transfer | K58: Completed
A59: 100608 | B59: 14/02/2025 | C59: =PROPER('Transactions Overview'!C65) -> Credit Card | D59: =PROPER('Transactions Overview'!D65) -> Boston | E59: Massachusetts | F59: =ABS('Transactions Overview'!F65) -> 566.37 | G59: Withdrawal | H59: Utilities | I59: PSEG | J59: =PROPER('Transactions Overview'!J65) -> Cash | K59: Completed
A60: 106011 | B60: 45501 | C60: =PROPER('Transactions Overview'!C66) -> Checking | D60: =PROPER('Transactions Overview'!D66) -> White Plains | E60: New York | F60: =ABS('Transactions Overview'!F66) -> 408.3 | G60: Transfer | H60: Transfers | I60: Venmo | J60: Debit Card | K60: Completed
A61: 104819 | B61: 45111 | C61: =PROPER('Transactions Overview'!C67) -> Credit Card | D61: =PROPER('Transactions Overview'!D67) -> Boston | E61: Massachusetts | F61: =ABS('Transactions Overview'!F67) -> 473.42 | G61: Payment | H61: =PROPER('Transactions Overview'!H67) -> Salary | I61: Payroll Deposit | J61: =PROPER('Transactions Overview'!J67) | K61: Completed
A62: 103239 | B62: 45390 | C62: Credit Card | D62: =PROPER('Transactions Overview'!D69) -> New York | E62: New York | F62: =ABS('Transactions Overview'!F69) -> 2193.75 | G62: Fee | H62: =PROPER('Transactions Overview'!H69) -> Utilities | I62: Con Edison | J62: =PROPER('Transactions Overview'!J69) -> Cash | K62: Completed
A63: 105901 | B63: 45268 | C63: =PROPER('Transactions Overview'!C70) -> Savings | D63: =PROPER('Transactions Overview'!D70) -> Newark | E63: New Jersey | F63: =ABS('Transactions Overview'!F70) -> 999.18 | G63: Deposit | H63: =PROPER('Transactions Overview'!H70) -> Entertainment | I63: Hulu | J63: =PROPER('Transactions Overview'!J70) -> Debit Card | K63: Completed
A64: 100770 | B64: 45064 | C64: =PROPER('Transactions Overview'!C71) -> Credit Card | D64: =PROPER('Transactions Overview'!D71) -> Hartford | E64: Connecticut | F64: =ABS('Transactions Overview'!F71) -> 425.84 | G64: Deposit | H64: =PROPER('Transactions Overview'!H71) -> Utilities | I64: Verizon Fios | J64: =PROPER('Transactions Overview'!J71) -> Check | K64: Completed
A65: 102479 | B65: 18/07/2026 | C65: =PROPER('Transactions Overview'!C73) -> Savings | D65: =PROPER('Transactions Overview'!D73) -> Philadelphia | E65: Pennsylvania | F65: =ABS('Transactions Overview'!F73) -> 1306.87 | G65: Payment | H65: =PROPER('Transactions Overview'!H73) -> Fees | I65: Monthly Maintenance Fee | J65: =PROPER('Transactions Overview'!J73) -> Credit Card | K65: Completed
A66: 108864 | B66: 45749 | C66: =PROPER('Transactions Overview'!C74) -> Savings | D66: =PROPER('Transactions Overview'!D74) -> Boston | E66: Massachusetts | F66: =ABS('Transactions Overview'!F74) -> 2095.22 | G66: Transfer | H66: =PROPER('Transactions Overview'!H74) -> Groceries | I66: Whole Foods | J66: ACH | K66: Completed
A67: 102559 | B67: 46205 | C67: =PROPER('Transactions Overview'!C75) -> Savings | D67: =PROPER('Transactions Overview'!D75) -> White Plains | E67: New York | F67: =ABS('Transactions Overview'!F75) -> 1313.32 | G67: Payment | H67: =PROPER('Transactions Overview'!H75) -> Insurance | I67: State Farm | J67: =PROPER('Transactions Overview'!J75) -> Debit Card | K67: Completed
A68: 107141 | B68: 44853 | C68: =PROPER('Transactions Overview'!C76) -> Savings | D68: =PROPER('Transactions Overview'!D76) -> Brooklyn | E68: New York | F68: =ABS('Transactions Overview'!F76) -> 2691.73 | G68: Transfer | H68: Entertainment | I68: Spotify | J68: Wire Transfer | K68: Completed
A69: 107030 | B69: 44741 | C69: =PROPER('Transactions Overview'!C77) -> Savings | D69: =PROPER('Transactions Overview'!D77) -> Newark | E69: New Jersey | F69: =ABS('Transactions Overview'!F77) -> 1671.85 | G69: Deposit | H69: =PROPER('Transactions Overview'!H77) | I69: Late Fee | J69: =PROPER('Transactions Overview'!J77) -> Cash | K69: Completed
A70: 101540 | B70: 45568 | C70: =PROPER('Transactions Overview'!C78) -> Credit Card | D70: =PROPER('Transactions Overview'!D78) -> Boston | E70: Massachusetts | F70: =ABS('Transactions Overview'!F78) -> 1233.42 | G70: Fee | H70: =PROPER('Transactions Overview'!H78) -> Transfers | I70: Zelle Transfer | J70: ACH
A71: 109504 | B71: 45234 | C71: =PROPER('Transactions Overview'!C79) -> Money Market | D71: =PROPER('Transactions Overview'!D79) -> Trenton | E71: New Jersey | F71: =ABS('Transactions Overview'!F79) -> 1547.09 | G71: Transfer | H71: =PROPER('Transactions Overview'!H79) -> Groceries | I71: Whole Foods | J71: ACH | K71: Completed
A72: 103706 | B72: 45815 | C72: =PROPER('Transactions Overview'!C80) -> Credit Card | D72: =PROPER('Transactions Overview'!D80) -> Hicksville | E72: New York | F72: =ABS('Transactions Overview'!F80) -> 215.96 | G72: Withdrawal | H72: Transportation | I72: Shell Gas Station | J72: ACH | K72: Completed
A73: 108776 | B73: 44770 | C73: =PROPER('Transactions Overview'!C81) -> Money Market | D73: =PROPER('Transactions Overview'!D81) -> Hartford | E73: Connecticut | F73: =ABS('Transactions Overview'!F81) -> 1249.02 | G73: Transfer | H73: =PROPER('Transactions Overview'!H81) -> Rent | I73: Rent Payment | J73: Check | K73: Completed
A74: 100688 | B74: 45129 | C74: =PROPER('Transactions Overview'!C82) -> Money Market | D74: =PROPER('Transactions Overview'!D82) -> Boston | E74: Massachusetts | F74: =ABS('Transactions Overview'!F82) -> 1403.42 | G74: Transfer | H74: =PROPER('Transactions Overview'!H82) -> Insurance | I74: Blue Cross Blue Shield | J74: =PROPER('Transactions Overview'!J82) -> Wire Transfer | K74: Completed
A75: 103084 | B75: 45980 | C75: =PROPER('Transactions Overview'!C83) -> Checking | D75: =PROPER('Transactions Overview'!D83) -> Newark | E75: New Jersey | F75: =ABS('Transactions Overview'!F83) -> 2936.01 | G75: Payment | H75: =PROPER('Transactions Overview'!H83) -> Healthcare | I75: Walgreens | J75: Check | K75: Pending
A76: 107850 | B76: 45985 | C76: =PROPER('Transactions Overview'!C84) -> Credit Card | D76: =PROPER('Transactions Overview'!D84) -> Boston | E76: Massachusetts | F76: =ABS('Transactions Overview'!F84) -> 209.7 | G76: Withdrawal | H76: =PROPER('Transactions Overview'!H84) -> Salary | I76: Payroll Deposit | J76: =PROPER('Transactions Overview'!J84) -> Check | K76: Completed
A77: 103327 | B77: 45724 | C77: =PROPER('Transactions Overview'!C85) -> Money Market | D77: =PROPER('Transactions Overview'!D85) -> Jersey City | E77: New Jersey | F77: =ABS('Transactions Overview'!F85) -> 1322.87 | G77: Withdrawal | H77: =PROPER('Transactions Overview'!H85) -> Healthcare | I77: Quest Diagnostics | J77: =PROPER('Transactions Overview'!J85) -> Debit Card | K77: Completed
A78: 109368 | B78: 44702 | C78: =PROPER('Transactions Overview'!C86) -> Checking | D78: =PROPER('Transactions Overview'!D86) -> Stamford | E78: Connecticut | F78: =ABS('Transactions Overview'!F86) -> 1456.29 | G78: Withdrawal | H78: =PROPER('Transactions Overview'!H86) -> Insurance | I78: Geico | J78: =PROPER('Transactions Overview'!J86) -> Credit Card | K78: Completed
A79: 110167 | B79: 45968 | C79: =PROPER('Transactions Overview'!C87) -> Savings | D79: =PROPER('Transactions Overview'!D87) -> Jersey City | E79: New Jersey | F79: =ABS('Transactions Overview'!F87) -> 398.28 | G79: Payment | H79: Rent | I79: Rent Payment | J79: =PROPER('Transactions Overview'!J87) -> Debit Card | K79: Completed
A80: 101658 | B80: 44900 | C80: =PROPER('Transactions Overview'!C89) -> Money Market | D80: =PROPER('Transactions Overview'!D89) -> Trenton | E80: New Jersey | F80: =ABS('Transactions Overview'!F89) -> 2661.14 | G80: Transfer | H80: =PROPER('Transactions Overview'!H89) -> Insurance | I80: Blue Cross Blue Shield | J80: =PROPER('Transactions Overview'!J89) -> Debit Card | K80: Completed
A81: 107428 | B81: 44777 | C81: =PROPER('Transactions Overview'!C90) -> Savings | D81: =PROPER('Transactions Overview'!D90) -> Stamford | E81: Connecticut | F81: =ABS('Transactions Overview'!F90) -> 2427.48 | G81: Transfer | H81: Utilities | I81: Con Edison | J81: =PROPER('Transactions Overview'!J90) | K81: Completed
A82: 102802 | B82: 45623 | C82: =PROPER('Transactions Overview'!C91) -> Credit Card | D82: =PROPER('Transactions Overview'!D91) -> New York | E82: New York | F82: =ABS('Transactions Overview'!F91) -> 2865.48 | G82: Transfer | H82: =PROPER('Transactions Overview'!H91) -> Insurance | I82: State Farm | J82: =PROPER('Transactions Overview'!J91) -> Cash | K82: Completed
A83: 108937 | B83: 45398 | C83: =PROPER('Transactions Overview'!C92) -> Savings | D83: =PROPER('Transactions Overview'!D92) -> Boston | E83: Massachusetts | F83: =ABS('Transactions Overview'!F92) -> 272.38 | G83: Transfer | H83: Groceries | I83: Trader Joe's | J83: =PROPER('Transactions Overview'!J92) -> Wire Transfer | K83: Completed
A84: 109304 | B84: 45245 | C84: =PROPER('Transactions Overview'!C93) -> Checking | D84: =PROPER('Transactions Overview'!D93) -> Brooklyn | E84: New York | F84: =ABS('Transactions Overview'!F93) -> 1894.59 | G84: Deposit | H84: =PROPER('Transactions Overview'!H93) -> Salary | I84: Payroll Deposit | J84: =PROPER('Transactions Overview'!J93) -> Credit Card | K84: Completed
A85: 107949 | B85: 13/07/2022 | C85: =PROPER('Transactions Overview'!C94) -> Credit Card | D85: =PROPER('Transactions Overview'!D94) -> Hartford | E85: Connecticut | F85: =ABS('Transactions Overview'!F94) -> 2476.37 | G85: Deposit | H85: =PROPER('Transactions Overview'!H94) -> Rent | I85: Rent Payment | J85: =PROPER('Transactions Overview'!J94) -> Credit Card | K85: Completed
A86: 107034 | B86: 29/04/2025 | C86: =PROPER('Transactions Overview'!C95) -> Money Market | D86: =PROPER('Transactions Overview'!D95) -> White Plains | E86: New York | F86: =ABS('Transactions Overview'!F95) -> 1497.67 | G86: Deposit | H86: =PROPER('Transactions Overview'!H95) -> Transportation | I86: EZ-Pass | J86: =PROPER('Transactions Overview'!J95) -> Debit Card | K86: Completed
A87: 100404 | B87: 46229 | C87: =PROPER('Transactions Overview'!C96) -> Savings | D87: =PROPER('Transactions Overview'!D96) -> Trenton | E87: New Jersey | F87: =ABS('Transactions Overview'!F96) -> 1857.82 | G87: Transfer | H87: Transportation | I87: MTA | J87: Wire Transfer | K87: Completed
A88: 107082 | B88: 44976 | C88: =PROPER('Transactions Overview'!C97) -> Savings | D88: =PROPER('Transactions Overview'!D97) -> Hicksville | E88: New York | F88: =ABS('Transactions Overview'!F97) -> 2078.24 | G88: Transfer | H88: =PROPER('Transactions Overview'!H97) -> Healthcare | I88: Quest Diagnostics | J88: =PROPER('Transactions Overview'!J97) -> Check | K88: Completed
A89: 109681 | B89: 45938 | C89: =PROPER('Transactions Overview'!C98) -> Savings | D89: =PROPER('Transactions Overview'!D98) -> Jersey City | E89: New Jersey | F89: =ABS('Transactions Overview'!F98) -> 2499.11 | G89: Deposit | H89: =PROPER('Transactions Overview'!H98) -> Entertainment | I89: Spotify | J89: =PROPER('Transactions Overview'!J98) -> Wire Transfer | K89: Completed
A90: 103780 | B90: 45788 | C90: =PROPER('Transactions Overview'!C100) -> Savings | D90: =PROPER('Transactions Overview'!D100) -> Jersey City | E90: New Jersey | F90: =ABS('Transactions Overview'!F100) -> 1224.72 | G90: Withdrawal | H90: =PROPER('Transactions Overview'!H100) -> Healthcare | I90: Walgreens | J90: =PROPER('Transactions Overview'!J100) -> Check | K90: Completed
A91: 102487 | B91: 44947 | C91: =PROPER('Transactions Overview'!C101) -> Money Market | D91: =PROPER('Transactions Overview'!D101) -> Stamford | E91: Connecticut | F91: =ABS('Transactions Overview'!F101) -> 643.21 | G91: Deposit | H91: =PROPER('Transactions Overview'!H101) -> Dining | I91: DoorDash | J91: =PROPER('Transactions Overview'!J101) -> Wire Transfer | K91: Completed
A92: 105630 | B92: 44883 | C92: =PROPER('Transactions Overview'!C102) -> Credit Card | D92: =PROPER('Transactions Overview'!D102) -> Hartford | E92: Connecticut | F92: =ABS('Transactions Overview'!F102) -> 2447.6 | G92: Payment | H92: =PROPER('Transactions Overview'!H102) -> Groceries | I92: Costco | J92: ACH | K92: Completed
A93: 102135 | B93: 44994 | C93: =PROPER('Transactions Overview'!C104) -> Credit Card | D93: =PROPER('Transactions Overview'!D104) -> Trenton | E93: New Jersey | F93: =ABS('Transactions Overview'!F104) -> 742.92 | G93: Deposit | H93: =PROPER('Transactions Overview'!H104) | I93: Payroll Deposit | J93: ACH | K93: Completed
A94: 103834 | B94: 45969 | C94: Money Market | D94: =PROPER('Transactions Overview'!D106) -> Trenton | E94: New Jersey | F94: =ABS('Transactions Overview'!F106) -> 1174.72 | G94: Transfer | H94: =PROPER('Transactions Overview'!H106) -> Transfers | I94: Internal Transfer | J94: Debit Card | K94: Completed
A95: 104783 | B95: 45780 | C95: =PROPER('Transactions Overview'!C107) -> Savings | D95: =PROPER('Transactions Overview'!D107) -> Jersey City | E95: New Jersey | F95: =ABS('Transactions Overview'!F107) -> 2301.89 | G95: Transfer | H95: =PROPER('Transactions Overview'!H107) -> Utilities | I95: National Grid | J95: =PROPER('Transactions Overview'!J107) -> Check | K95: Pending
A96: 102551 | B96: 45711 | C96: =PROPER('Transactions Overview'!C108) -> Credit Card | D96: =PROPER('Transactions Overview'!D108) -> Philadelphia | E96: Pennsylvania | F96: =ABS('Transactions Overview'!F108) -> 2382.48 | G96: Withdrawal | H96: =PROPER('Transactions Overview'!H108) -> Shopping | I96: Amazon | J96: Credit Card | K96: Completed
A97: 100094 | B97: 44719 | C97: =PROPER('Transactions Overview'!C109) -> Credit Card | D97: =PROPER('Transactions Overview'!D109) -> New York | E97: New York | F97: =ABS('Transactions Overview'!F109) -> 2236.31 | G97: Deposit | H97: =PROPER('Transactions Overview'!H109) -> Transportation | I97: Uber | J97: =PROPER('Transactions Overview'!J109) -> Check | K97: Completed
A98: 103104 | B98: 45722 | C98: =PROPER('Transactions Overview'!C110) -> Savings | D98: =PROPER('Transactions Overview'!D110) -> Stamford | E98: Connecticut | F98: =ABS('Transactions Overview'!F110) -> 2184.55 | G98: Transfer | H98: =PROPER('Transactions Overview'!H110) -> Entertainment | I98: Spotify | J98: =PROPER('Transactions Overview'!J110) -> Credit Card | K98: Completed
A99: 105850 | B99: 45728 | C99: =PROPER('Transactions Overview'!C111) -> Savings | D99: =PROPER('Transactions Overview'!D111) -> White Plains | E99: New York | F99: =ABS('Transactions Overview'!F111) -> 1104.76 | G99: Payment | H99: =PROPER('Transactions Overview'!H111) -> Groceries | I99: ShopRite | J99: =PROPER('Transactions Overview'!J111) -> Check | K99: Completed
A100: 101551 | B100: 46060 | C100: =PROPER('Transactions Overview'!C112) -> Money Market | D100: =PROPER('Transactions Overview'!D112) -> Philadelphia | E100: Pennsylvania | F100: =ABS('Transactions Overview'!F112) -> 887.02 | G100: Deposit | H100: =PROPER('Transactions Overview'!H112) -> Utilities | I100: Verizon Fios | J100: =PROPER('Transactions Overview'!J112) -> Cash | K100: Completed
...

Sheet Transactions (Cleaned)
A1: transaction_id | B1: transaction_date | C1: account_type | D1: branch_city | E1: branch_state | F1: amount | G1: transaction_type | H1: category | I1: merchant | J1: payment_method | K1: status
A2: 106499 | B2: 45992 | C2: Money Market | D2: Albany | E2: New York | F2: 2282.09 | G2: Payment | H2: Transportation | I2: EZ-Pass | J2: Wire Transfer | K2: Completed
A3: 101635 | B3: 45715 | C3: Savings | D3: Philadelphia | E3: Pennsylvania | F3: 431.86 | G3: Transfer | H3: Transportation | I3: Lyft | K3: Pending
A4: 102938 | B4: 45443 | C4: Checking | D4: Stamford | E4: Connecticut | F4: 277.69 | G4: Transfer | H4: Shopping | I4: Amazon | J4: Cash | K4: Completed
A5: 110478 | B5: 44762 | C5: Credit Card | D5: New York | E5: New York | F5: 2999.37 | G5: Transfer | H5: Shopping | I5: Target | J5: Cash | K5: Completed
A6: 100906 | B6: 45254 | C6: Savings | D6: Hartford | E6: Connecticut | F6: 1087.05 | G6: Withdrawal | H6: Fees | I6: Late Fee | J6: Cash | K6: Completed
A7: 104027 | B7: 45903 | C7: Money Market | D7: Jersey City | E7: New Jersey | F7: 102.75 | G7: Withdrawal | H7: Utilities | I7: PSEG | J7: Debit Card | K7: Pending
A8: 105516 | B8: 45794 | C8: Credit Card | D8: New York | E8: New York | F8: 1605.73 | G8: Fee | H8: Rent | I8: Rent Payment | J8: Cash | K8: Completed
A9: 108794 | B9: 45906 | C9: Credit Card | D9: Newark | E9: New Jersey | F9: 486.99 | G9: Deposit | H9: Fees | I9: Late Fee | J9: Debit Card | K9: Completed
A10: 107911 | B10: 44687 | C10: Checking | D10: Philadelphia | E10: Pennsylvania | F10: 1844.79 | G10: Payment | H10: Fees | I10: Late Fee | J10: Cash | K10: Completed
A11: 105279 | B11: 45774 | C11: Money Market | D11: Hicksville | E11: New York | F11: 2495.04 | G11: Withdrawal | H11: Utilities | I11: National Grid | J11: Cash | K11: Completed
A12: 108373 | B12: 45968 | C12: Credit Card | D12: Boston | E12: Massachusetts | F12: 3060.68 | G12: Deposit | H12: Groceries | I12: Stop & Shop | J12: Wire Transfer | K12: Completed
A13: 102618 | B13: 45346 | C13: Credit Card | D13: Trenton | E13: New Jersey | F13: 2562.89 | G13: Transfer | H13: Entertainment | I13: Hulu | J13: Cash | K13: Completed
A14: 105580 | B14: 45522 | C14: Checking | D14: Albany | E14: New York | F14: 1344.25 | G14: Withdrawal | H14: Transportation | I14: EZ-Pass | J14: Check | K14: Completed
A15: 101092 | B15: 45096 | C15: Savings | D15: Trenton | E15: New Jersey | F15: 133.77 | G15: Withdrawal | H15: Groceries | I15: Stop & Shop | J15: Wire Transfer | K15: Completed
... A28: 106340 | B28: 45341 | C28: Money Market | D28: Trenton | E28: New Jersey | F28: 118.5 | G28: Deposit | H28: Dining | I28: Chipotle | J28: Credit Card | K28: Completed
A29: 105305 | B29: 45571 | C29: Checking | D29: Boston | E29: Massachusetts | F29: 821.76 | G29: Payment | H29: Entertainment | I29: Steam | K29: Completed
A30: 108240 | B30: 46117 | C30: Money Market | D30: Philadelphia | E30: Pennsylvania | F30: 1601.03 | G30: Payment | H30: Entertainment | I30: Netflix | J30: Check | K30: Completed
A31: 100840 | B31: 44690 | C31: Credit Card | D31: Trenton | E31: New Jersey | F31: 219.92 | G31: Withdrawal | H31: Dining | I31: Chipotle | J31: ACH | K31: Completed
A32: 108931 | B32: 45608 | C32: Savings | D32: Philadelphia | E32: Pennsylvania | F32: 685.09 | G32: Payment | H32: Shopping | I32: Walmart | J32: Wire Transfer | K32: Completed
A33: 101832 | B33: 44974 | C33: Money Market | D33: Albany | E33: New York | F33: 326.64 | G33: Withdrawal | H33: Healthcare | I33: Walgreens | J33: ACH | K33: Pending
A34: 105588 | B34: 44671 | C34: Checking | D34: Albany | E34: New York | F34: 2788.39 | G34: Payment | H34: Insurance | I34: State Farm | J34: ACH | K34: Completed
A35: 101703 | B35: 45556 | C35: Credit Card | D35: New York | E35: New York | F35: 2600.4 | G35: Payment | H35: Shopping | I35: Target | J35: Debit Card | K35: Completed
A36: 102630 | B36: 44912 | C36: Credit Card | D36: Philadelphia | E36: Pennsylvania | F36: 2251.77 | G36: Fee | H36: Fees | I36: ATM Fee | J36: Credit Card | K36: Completed
A37: 108467 | B37: 44984 | C37: Money Market | D37: Albany | E37: New York | F37: 964.9 | G37: Withdrawal | H37: Healthcare | I37: Copay - Dr. Visit | J37: Wire Transfer | K37: Completed
A38: 107547 | B38: 46077 | C38: Credit Card | D38: Trenton | E38: New Jersey | F38: 2840.57 | G38: Payment | H38: Transfers | I38: Zelle Transfer | J38: Cash | K38: Completed
A39: 100499 | B39: 46178 | C39: Money Market | D39: Albany | E39: New York | F39: 393.53 | G39: Payment | H39: Insurance | I39: Geico | J39: Wire Transfer | K39: Completed
A40: 102987 | B40: 45826 | C40: Money Market | D40: Stamford | E40: Connecticut | F40: 2529.06 | G40: Deposit | H40: Groceries | I40: Trader Joe's | J40: ACH | K40: Completed
A41: 101550 | B41: 46254 | C41: Checking | D41: Philadelphia | E41: Pennsylvania | F41: 303.04 | G41: Withdrawal | H41: Shopping | I41: Best Buy | J41: Cash | K41: Completed
... A49: 109805 | B49: 45867 | C49: Money Market | D49: Albany | E49: New York | F49: 3055.5 | G49: Transfer | H49: Healthcare | I49: Copay - Dr. Visit | J49: Check | K49: Completed
A50: 103004 | B50: 45388 | C50: Savings | D50: New York | E50: New York | F50: 1219.92 | G50: Transfer | H50: Healthcare | J50: Cash | K50: Completed
A51: 103330 | B51: 45860 | C51: Savings | D51: Trenton | E51: New Jersey | F51: 2618.76 | G51: Fee | H51: Fees | I51: ATM Fee | J51: Credit Card | K51: Completed
A52: 101632 | B52: 45261 | C52: Savings | D52: Newark | E52: New Jersey | F52: 2901.12 | G52: Payment | H52: Dining | I52: Local Diner | J52: Cash | K52: Completed
A53: 102146 | B53: 45305 | C53: Checking | D53: Trenton | E53: New Jersey | F53: 3004.07 | G53: Deposit | H53: Transfers | I53: Zelle Transfer | J53: Cash | K53: Completed
A54: 103451 | B54: 44657 | C54: Savings | D54: Albany | E54: New York | F54: 760.84 | G54: Withdrawal | H54: Healthcare | J54: ACH | K54: Completed
A55: 106969 | B55: 45097 | C55: Credit Card | D55: Albany | E55: New York | F55: 883.46 | G55: Deposit | H55: Insurance | I55: Geico | J55: Check | K55: Completed
A56: 108191 | B56: 45150 | C56: Money Market | D56: New York | E56: New York | F56: 2262.11 | G56: Payment | H56: Transfers | I56: Internal Transfer | J56: Wire Transfer | K56: Failed
A57: 106446 | B57: 44803 | C57: Credit Card | D57: Trenton | E57: New Jersey | F57: 2134.87 | G57: Transfer | H57: Entertainment | I57: AMC Theatres | J57: ACH | K57: Completed
A58: 102187 | B58: 44752 | C58: Money Market | D58: Hartford | E58: Connecticut | F58: 2268.98 | G58: Transfer | H58: Shopping | I58: Target | J58: Wire Transfer | K58: Completed
A59: 100608 | B59: 45702 | C59: Credit Card | D59: Boston | E59: Massachusetts | F59: 566.37 | G59: Withdrawal | H59: Utilities | I59: PSEG | J59: Cash | K59: Completed
A60: 106011 | B60: 45501 | C60: Checking | D60: White Plains | E60: New York | F60: 408.3 | G60: Transfer | H60: Transfers | I60: Venmo | J60: Debit Card | K60: Completed
A61: 104819 | B61: 45111 | C61: Credit Card | D61: Boston | E61: Massachusetts | F61: 473.42 | G61: Payment | H61: Salary | I61: Payroll Deposit | K61: Completed
A62: 103239 | B62: 45390 | C62: Credit Card | D62: New York | E62: New York | F62: 2193.75 | G62: Fee | H62: Utilities | I62: Con Edison | J62: Cash | K62: Completed
A63: 105901 | B63: 45268 | C63: Savings | D63: Newark | E63: New Jersey | F63: 999.18 | G63: Deposit | H63: Entertainment | I63: Hulu | J63: Debit Card | K63: Completed
A64: 100770 | B64: 45064 | C64: Credit Card | D64: Hartford | E64: Connecticut | F64: 425.84 | G64: Deposit | H64: Utilities | I64: Verizon Fios | J64: Check | K64: Completed
A65: 102479 | B65: 46221 | C65: Savings | D65: Philadelphia | E65: Pennsylvania | F65: 1306.87 | G65: Payment | H65: Fees | I65: Monthly Maintenance Fee | J65: Credit Card | K65: Completed
A66: 108864 | B66: 45749 | C66: Savings | D66: Boston | E66: Massachusetts | F66: 2095.22 | G66: Transfer | H66: Groceries | I66: Whole Foods | J66: ACH | K66: Completed
A67: 102559 | B67: 46205 | C67: Savings | D67: White Plains | E67: New York | F67: 1313.32 | G67: Payment | H67: Insurance | I67: State Farm | J67: Debit Card | K67: Completed
A68: 107141 | B68: 44853 | C68: Savings | D68: Brooklyn | E68: New York | F68: 2691.73 | G68: Transfer | H68: Entertainment | I68: Spotify | J68: Wire Transfer | K68: Completed
A69: 107030 | B69: 44741 | C69: Savings | D69: Newark | E69: New Jersey | F69: 1671.85 | G69: Deposit | I69: Late Fee | J69: Cash | K69: Completed
A70: 101540 | B70: 45568 | C70: Credit Card | D70: Boston | E70: Massachusetts | F70: 1233.42 | G70: Fee | H70: Transfers | I70: Zelle Transfer | J70: ACH
A71: 109504 | B71: 45234 | C71: Money Market | D71: Trenton | E71: New Jersey | F71: 1547.09 | G71: Transfer | H71: Groceries | I71: Whole Foods | J71: ACH | K71: Completed
A72: 103706 | B72: 45815 | C72: Credit Card | D72: Hicksville | E72: New York | F72: 215.96 | G72: Withdrawal | H72: Transportation | I72: Shell Gas Station | J72: ACH | K72: Completed
A73: 108776 | B73: 44770 | C73: Money Market | D73: Hartford | E73: Connecticut | F73: 1249.02 | G73: Transfer | H73: Rent | I73: Rent Payment | J73: Check | K73: Completed
A74: 100688 | B74: 45129 | C74: Money Market | D74: Boston | E74: Massachusetts | F74: 1403.42 | G74: Transfer | H74: Insurance | I74: Blue Cross Blue Shield | J74: Wire Transfer | K74: Completed
A75: 103084 | B75: 45980 | C75: Checking | D75: Newark | E75: New Jersey | F75: 2936.01 | G75: Payment | H75: Healthcare | I75: Walgreens | J75: Check | K75: Pending
A76: 107850 | B76: 45985 | C76: Credit Card | D76: Boston | E76: Massachusetts | F76: 209.7 | G76: Withdrawal | H76: Salary | I76: Payroll Deposit | J76: Check | K76: Completed
A77: 103327 | B77: 45724 | C77: Money Market | D77: Jersey City | E77: New Jersey | F77: 1322.87 | G77: Withdrawal | H77: Healthcare | I77: Quest Diagnostics | J77: Debit Card | K77: Completed
A78: 109368 | B78: 44702 | C78: Checking | D78: Stamford | E78: Connecticut | F78: 1456.29 | G78: Withdrawal | H78: Insurance | I78: Geico | J78: Credit Card | K78: Completed
A79: 110167 | B79: 45968 | C79: Savings | D79: Jersey City | E79: New Jersey | F79: 398.28 | G79: Payment | H79: Rent | I79: Rent Payment | J79: Debit Card | K79: Completed
A80: 101658 | B80: 44900 | C80: Money Market | D80: Trenton | E80: New Jersey | F80: 2661.14 | G80: Transfer | H80: Insurance | I80: Blue Cross Blue Shield | J80: Debit Card | K80: Completed
A81: 107428 | B81: 44777 | C81: Savings | D81: Stamford | E81: Connecticut | F81: 2427.48 | G81: Transfer | H81: Utilities | I81: Con Edison | K81: Completed
A82: 102802 | B82: 45623 | C82: Credit Card | D82: New York | E82: New York | F82: 2865.48 | G82: Transfer | H82: Insurance | I82: State Farm | J82: Cash | K82: Completed
A83: 108937 | B83: 45398 | C83: Savings | D83: Boston | E83: Massachusetts | F83: 272.38 | G83: Transfer | H83: Groceries | I83: Trader Joe's | J83: Wire Transfer | K83: Completed
A84: 109304 | B84: 45245 | C84: Checking | D84: Brooklyn | E84: New York | F84: 1894.59 | G84: Deposit | H84: Salary | I84: Payroll Deposit | J84: Credit Card | K84: Completed
A85: 107949 | B85: 44755 | C85: Credit Card | D85: Hartford | E85: Connecticut | F85: 2476.37 | G85: Deposit | H85: Rent | I85: Rent Payment | J85: Credit Card | K85: Completed
A86: 107034 | B86: 45776 | C86: Money Market | D86: White Plains | E86: New York | F86: 1497.67 | G86: Deposit | H86: Transportation | I86: EZ-Pass | J86: Debit Card | K86: Completed
A87: 100404 | B87: 46229 | C87: Savings | D87: Trenton | E87: New Jersey | F87: 1857.82 | G87: Transfer | H87: Transportation | I87: MTA | J87: Wire Transfer | K87: Completed
A88: 107082 | B88: 44976 | C88: Savings | D88: Hicksville | E88: New York | F88: 2078.24 | G88: Transfer | H88: Healthcare | I88: Quest Diagnostics | J88: Check | K88: Completed
A89: 109681 | B89: 45938 | C89: Savings | D89: Jersey City | E89: New Jersey | F89: 2499.11 | G89: Deposit | H89: Entertainment | I89: Spotify | J89: Wire Transfer | K89: Completed
A90: 103780 | B90: 45788 | C90: Savings | D90: Jersey City | E90: New Jersey | F90: 1224.72 | G90: Withdrawal | H90: Healthcare | I90: Walgreens | J90: Check | K90: Completed
A91: 102487 | B91: 44947 | C91: Money Market | D91: Stamford | E91: Connecticut | F91: 643.21 | G91: Deposit | H91: Dining | I91: DoorDash | J91: Wire Transfer | K91: Completed
A92: 105630 | B92: 44883 | C92: Credit Card | D92: Hartford | E92: Connecticut | F92: 2447.6 | G92: Payment | H92: Groceries | I92: Costco | J92: ACH | K92: Completed
A93: 102135 | B93: 44994 | C93: Credit Card | D93: Trenton | E93: New Jersey | F93: 742.92 | G93: Deposit | I93: Payroll Deposit | J93: ACH | K93: Completed
A94: 103834 | B94: 45969 | C94: Money Market | D94: Trenton | E94: New Jersey | F94: 1174.72 | G94: Transfer | H94: Transfers | I94: Internal Transfer | J94: Debit Card | K94: Completed
A95: 104783 | B95: 45780 | C95: Savings | D95: Jersey City | E95: New Jersey | F95: 2301.89 | G95: Transfer | H95: Utilities | I95: National Grid | J95: Check | K95: Pending
A96: 102551 | B96: 45711 | C96: Credit Card | D96: Philadelphia | E96: Pennsylvania | F96: 2382.48 | G96: Withdrawal | H96: Shopping | I96: Amazon | J96: Credit Card | K96: Completed
A97: 100094 | B97: 44719 | C97: Credit Card | D97: New York | E97: New York | F97: 2236.31 | G97: Deposit | H97: Transportation | I97: Uber | J97: Check | K97: Completed
A98: 103104 | B98: 45722 | C98: Savings | D98: Stamford | E98: Connecticut | F98: 2184.55 | G98: Transfer | H98: Entertainment | I98: Spotify | J98: Credit Card | K98: Completed
A99: 105850 | B99: 45728 | C99: Savings | D99: White Plains | E99: New York | F99: 1104.76 | G99: Payment | H99: Groceries | I99: ShopRite | J99: Check | K99: Completed
A100: 101551 | B100: 46060 | C100: Money Market | D100: Philadelphia | E100: Pennsylvania | F100: 887.02 | G100: Deposit | H100: Utilities | I100: Verizon Fios | J100: Cash | K100: Completed
A101: 110424 | B101: 46212 | C101: Credit Card | D101: Boston | E101: Massachusetts | F101: 738.61 | G101: Transfer | H101: Transfers | I101: Internal Transfer | J101: Wire Transfer | K101: Completed
A102: 103098 | B102: 45686 | C102: Savings | D102: Philadelphia | E102: Pennsylvania | F102: 663.53 | G102: Withdrawal | H102: Shopping | I102: Amazon | J102: Check | K102: Completed
A103: 104316 | B103: 45918 | C103: Credit Card | D103: New York | E103: New York | F103: 1166.09 | G103: Transfer | H103: Transportation | I103: Lyft | J103: Check | K103: Completed
A104: 100604 | B104: 46214 | C104: Credit Card | D104: Philadelphia | E104: Pennsylvania | F104: 1185.7 | G104: Deposit | H104: Entertainment | I104: AMC Theatres | J104: Debit Card | K104: Completed
A105: 104049 | B105: 45371 | C105: Savings | D105: Philadelphia | E105: Pennsylvania | F105: 3169.36 | G105: Deposit | H105: Entertainment | I105: Steam | J105: Wire Transfer | K105: Completed
... A140: 103727 | B140: 44911 | C140: Checking | D140: Brooklyn | E140: New York | F140: 333.31 | G140: Fee | H140: Fees | I140: Late Fee | J140: Wire Transfer | K140: Completed
A141: 101971 | B141: 45727 | C141: Checking | D141: Trenton | E141: New Jersey | F141: 533 | G141: Withdrawal | H141: Shopping | I141: Walmart | K141: Pending
A142: 110341 | B142: 45580 | C142: Credit Card | D142: Boston | E142: Massachusetts | F142: 717.01 | G142: Payment | H142: Healthcare | I142: CVS Pharmacy | J142: Wire Transfer | K142: Completed
A143: 105093 | B143: 45411 | C143: Savings | D143: Hartford | E143: Connecticut | F143: 1103.46 | G143: Transfer | H143: Rent | I143: Rent Payment | J143: Wire Transfer | K143: Completed
A144: 110171 | B144: 45580 | C144: Savings | D144: Boston | E144: Massachusetts | F144: 35.53 | G144: Withdrawal | H144: Insurance | I144: State Farm | J144: Wire Transfer | K144: Completed
A145: 100843 | B145: 44814 | C145: Credit Card | D145: Hartford | E145: Connecticut | F145: 3055.64 | G145: Payment | H145: Entertainment | I145: AMC Theatres | J145: ACH | K145: Completed
A146: 100812 | B146: 45636 | C146: Money Market | D146: Jersey City | E146: New Jersey | F146: 235.33 | G146: Withdrawal | H146: Utilities | I146: National Grid | J146: Debit Card | K146: Completed
A147: 103736 | B147: 44691 | C147: Savings | D147: Brooklyn | E147: New York | F147: 1655.32 | G147: Deposit | H147: Fees | I147: Late Fee | J147: Cash | K147: Completed
A148: 101801 | B148: 45251 | C148: Checking | D148: Hartford | E148: Connecticut | F148: 2484.99 | G148: Deposit | H148: Insurance | I148: Blue Cross Blue Shield | J148: Check | K148: Pending
A149: 109961 | B149: 45643 | C149: Savings | D149: Newark | E149: New Jersey | F149: 1030.7 | G149: Payment | H149: Entertainment | I149: Hulu | J149: ACH | K149: Completed
A150: 107541 | B150: 45235 | C150: Checking | D150: Albany | E150: New York | F150: 2116.36 | G150: Transfer | H150: Utilities | I150: Con Edison | J150: Check | K150: Completed
A151: 109569 | B151: 45084 | C151: Credit Card | D151: Trenton | E151: New Jersey | F151: 2278.39 | G151: Deposit | H151: Utilities | I151: National Grid | J151: Debit Card | K151: Completed
A152: 107720 | B152: 46161 | C152: Savings | D152: Philadelphia | E152: Pennsylvania | F152: 754.65 | G152: Withdrawal | H152: Rent | I152: Rent Payment | J152: Wire Transfer | K152: Completed
A153: 110106 | B153: 46020 | C153: Savings | D153: Newark | E153: New Jersey | F153: 2818.52 | G153: Withdrawal | H153: Transfers | I153: Zelle Transfer | J153: Debit Card | K153: Completed
...
