Workbook

Sheet finance_joined_tables
A1: account_id | B1: credit_score | C1: account_status | D1: transaction_id | E1: transaction_date | F1: category | G1: transaction_type | H1: payment_method | I1: status
A2: NULL | B2: NULL | C2: NULL | D2: 100001 | E2: 44700 | F2: fees | G2: Fee | H2: ach | I2: Completed
A3: 10357 | B3: 734 | C3: Active | D3: 100002 | E3: 45670 | F3: UTILITIES | G3: Payment | H3: CREDIT CARD | I3: Completed
A4: 10140 | B4: 600 | C4: Active | D4: 100003 | E4: 45873 | F4: Entertainmnt | G4: Payment | H4: ach | I4: Completed
A5: 10049 | B5: 765 | C5: Active | D5: 100004 | E5: 28/03/2022 | F5: Healthcare | G5: Payment | H5: Credit | I5: Completed
A6: 10544 | B6: 452 | C6: Closed | D6: 100005 | E6: 44853 | F6: salary | G6: Deposit | H6: ACH | I6: Completed
A7: 10415 | B7: 307 | C7: Active | D7: 100006 | E7: 45949 | F7: Utilities | G7: Payment | H7: DEBIT CARD | I7: Completed
A8: 10481 | B8: 331 | C8: Active | D8: 100007 | E8: 25/09/2022 | F8: ENTERTAINMENT | G8: Payment | H8: Debit | I8: Failed
A9: 10519 | B9: 363 | C9: Active | D9: 100008 | E9: 44820 | F9: insurance | G9: Payment | H9: Credit Card | I9: Completed
A10: 10560 | B10: 602 | C10: Active | D10: 100009 | E10: 45327 | F10: insurance | G10: Payment | H10: CHECK | I10: Completed
A11: 10328 | B11: 620 | C11: Active | D11: 100010 | E11: 44883 | F11: Dining | G11: Withdrawal | H11: DEBIT CARD | I11: Completed
A12: 10636 | B12: 756 | C12: Active | D12: 100011 | E12: 44929 | F12: Health Care | G12: Payment | H12: Check | I12: Completed
A13: 10437 | B13: 335 | C13: Active | D13: 100012 | E13: 45088 | F13: SALARY | G13: Deposit | H13: ach | I13: Completed
A14: NULL | B14: NULL | C14: NULL | D14: 100013 | E14: 15/11/2024 | F14: utilities | G14: Payment | H14: Debit | I14: Completed
A15: 10385 | B15: 679 | C15: Active | D15: 100014 | E15: 45080 | F15: Healthcare | G15: Payment | H15: credit card | I15: Completed
A16: 10168 | B16: 319 | C16: Active | D16: 100015 | E16: 44609 | F16: fees | G16: Fee | H16: ach | I16: Failed
A17: 10447 | B17: 387 | C17: Active | D17: 100016 | E17: 45694 | F17: UTILITIES | G17: Payment | H17: debit card | I17: Completed
A18: 10624 | B18: 640 | C18: Active | D18: 100017 | E18: 45362 | F18: utilities | G18: Payment | H18: Check | I18: Completed
A19: 10231 | B19: 419 | C19: Active | D19: 100018 | E19: 26/10/2024 | F19: shopping | G19: Payment | H19: debit card | I19: Completed
A20: 10249 | B20: 659 | C20: Active | D20: 100019 | E20: 45496 | F20: DINING | G20: Withdrawal | H20: credit card | I20: Completed
A21: 10459 | B21: 682 | C21: Active | D21: 100020 | E21: 45122 | F21: TRANSFER | G21: Transfer | H21: ach | I21: Completed
A22: 10334 | B22: 780 | C22: Closed | D22: 100021 | E22: 44616 | F22: Rent Payment | G22: Payment | H22: Wire Transfer | I22: Completed
A23: 10061 | B23: 837 | C23: Frozen | D23: 100022 | E23: 46023 | F23: HEALTHCARE | G23: Payment | H23: credit card | I23: Completed
A24: NULL | B24: NULL | C24: NULL | D24: 100023 | E24: 44876 | F24: healthcare | G24: Payment | H24: debit card | I24: Completed
A25: 10648 | B25: 319 | C25: Active | D25: 100024 | E25: 46133 | F25: Entertainmnt | G25: Payment | H25: Credit Card | I25: Completed
A26: 10375 | B26: 826 | C26: Active | D26: 100025 | E26: 45413 | F26: insurance | G26: Payment | H26: credit card | I26: Completed
A27: 10402 | B27: 710 | C27: Active | D27: 100026 | E27: 45012 | F27: RENT | G27: Payment | H27: check | I27: Completed
A28: 10065 | B28: 753 | C28: Active | D28: 100027 | E28: 45988 | F28: Transport | G28: Withdrawal | H28: CASH | I28: Completed
A29: 10458 | B29: 573 | C29: Active | D29: 100028 | E29: 44589 | F29: Entertainment | G29: Payment | H29: Credit | I29: Completed
A30: 10648 | B30: 319 | C30: Active | D30: 100029 | E30: 45235 | F30: Utility | G30: Payment | H30: CHECK | I30: Completed
A31: 10513 | B31: 568 | C31: Closed | D31: 100030 | E31: 45343 | F31: Insurance | G31: Payment | H31: Credit Card | I31: Completed
A32: 10271 | B32: 714 | C32: Active | D32: 100031 | E32: 46046 | F32: healthcare | G32: Payment | H32: Credit | I32: Completed
A33: 10293 | B33: 696 | C33: Closed | D33: 100032 | E33: 22/06/2024 | F33: TRANSPORTATION | G33: Withdrawal | H33: Credit Card | I33: Completed
A34: NULL | B34: NULL | C34: NULL | D34: 100033 | E34: 45330 | F34: insurance | G34: Payment | H34: check | I34: Completed
A35: 10178 | B35: 497 | C35: Active | D35: 100034 | E35: 45564 | F35: Payroll | G35: Deposit | H35: ach | I35: Pending
A36: 10436 | B36: 631 | C36: Active | D36: 100035 | E36: 45430 | F36: Shopping | G36: Withdrawal | H36: DEBIT CARD | I36: Completed
A37: NULL | B37: NULL | C37: NULL | D37: 100036 | E37: 46140 | F37: Rent Payment | G37: Payment | H37: wire | I37: Completed
A38: 10471 | B38: 448 | C38: Active | D38: 100037 | E38: 44744 | F38: rent | G38: Payment | I38: Pending
A39: NULL | B39: NULL | C39: NULL | D39: 100038 | E39: 45444 | F39: Utility | G39: Payment | H39: debit card | I39: Completed
A40: 10468 | B40: 756 | C40: Active | D40: 100039 | E40: 45399 | F40: healthcare | G40: Payment | H40: Check | I40: Completed
A41: 10260 | B41: 312 | C41: Active | D41: 100040 | E41: 44647 | F41: Rent | G41: Payment | H41: WIRE | I41: Pending
A42: 10042 | B42: 555 | C42: Active | D42: 100041 | E42: 44679 | F42: Dining | G42: Withdrawal | H42: Credit | I42: Completed
A43: 10436 | B43: 631 | C43: Active | D43: 100042 | E43: 31/08/2024 | F43: INSURANCE | G43: Payment | H43: ach | I43: Completed
A44: 10698 | B44: 427 | C44: Active | D44: 100043 | E44: 45331 | F44: Transfer | G44: Transfer | H44: wire | I44: Completed
A45: 10463 | B45: 611 | C45: Active | D45: 100044 | E45: 45518 | F45: Utilities | G45: Payment | H45: debit card | I45: Completed
A46: NULL | B46: NULL | C46: NULL | D46: 100045 | E46: 45537 | F46: transfer | G46: Transfer | H46: ach | I46: Completed
A47: 10416 | B47: 732 | C47: Active | D47: 100046 | E47: 45456 | F47: Entertainmnt | G47: Payment | H47: Debit Card | I47: Completed
A48: 10077 | B48: 448 | C48: Closed | D48: 100047 | E48: 45770 | F48: insurance | G48: Payment | H48: CHECK
A49: 10402 | B49: 710 | C49: Active | D49: 100048 | E49: 45010 | F49: healthcare | G49: Payment | H49: Credit Card | I49: Completed
A50: 10197 | B50: 315 | C50: Active | D50: 100049 | E50: 18/07/2026 | F50: dining | G50: Withdrawal | H50: CASH | I50: Completed
A51: 10363 | B51: 722 | C51: Closed | D51: 100050 | E51: 45950 | F51: HEALTHCARE | G51: Payment | H51: DEBIT CARD | I51: Completed
A52: 10447 | B52: 387 | C52: Active | D52: 100051 | E52: 44843 | F52: Health Care | G52: Payment | H52: credit card | I52: Completed
A53: 10545 | B53: 400 | C53: Active | D53: 100052 | E53: 44677 | F53: Rent Payment | G53: Payment | H53: Check | I53: Failed
A54: 10269 | B54: 716 | C54: Active | D54: 100053 | E54: 44915 | F54: Transfers | G54: Transfer | H54: Wire Transfer | I54: Completed
A55: 10269 | B55: 716 | C55: Active | D55: 100053 | E55: 44915 | F55: Transfers | G55: Transfer | H55: Wire Transfer | I55: Completed
A56: 10100 | B56: 448 | C56: Active | D56: 100054 | E56: 45544 | F56: salary | G56: Deposit | H56: ach | I56: Completed
A57: 10227 | B57: 773 | C57: Active | D57: 100055 | E57: 46225 | F57: Insurance | G57: Payment | H57: ACH | I57: Completed
A58: 10361 | B58: 460 | C58: Active | D58: 100056 | E58: 46104 | F58: Groceries | G58: Payment | H58: credit card | I58: Completed
A59: 10207 | B59: 516 | C59: Active | D59: 100057 | E59: 45202 | F59: INSURANCE | G59: Payment | H59: Credit Card | I59: Completed
A60: 10333 | B60: 554 | C60: Active | D60: 100058 | E60: 45836 | F60: Transport | G60: Payment | H60: credit card | I60: Completed
A61: 10525 | B61: 409 | C61: Active | D61: 100059 | E61: 45324 | F61: FEES | G61: Fee | H61: ach | I61: Completed
A62: 10572 | B62: 498 | C62: Active | D62: 100060 | E62: 14/07/2023 | F62: Utility | G62: Payment | H62: ach | I62: Failed
A63: 10035 | B63: 345 | C63: Active | D63: 100061 | E63: 17/03/2025 | F63: Salary | G63: Deposit | H63: ach | I63: Pending
A64: 10505 | B64: 381 | C64: Active | D64: 100062 | E64: 45968 | F64: Insurance | G64: Payment | H64: ach | I64: Completed
A65: 10060 | B65: 613 | C65: Active | D65: 100063 | E65: 19/07/2023 | F65: transportation | G65: Payment | H65: Cash | I65: Pending
A66: 10141 | B66: 665 | C66: Active | D66: 100064 | E66: 45571 | G66: Withdrawal | H66: Credit | I66: Completed
A67: NULL | B67: NULL | C67: NULL | D67: 100065 | E67: 46000 | F67: insurance | G67: Payment | H67: Credit Card | I67: Completed
A68: NULL | B68: NULL | C68: NULL | D68: 100066 | E68: 44793 | F68: Dining | G68: Payment | H68: Credit | I68: Completed
A69: 10597 | B69: 800 | C69: Active | D69: 100067 | E69: 45561 | F69: Groceries | G69: Payment | H69: CREDIT CARD | I69: Completed
A70: 10515 | B70: 499 | C70: Active | D70: 100068 | E70: 44576 | F70: utilities | G70: Payment | H70: CHECK | I70: Completed
A71: NULL | B71: NULL | C71: NULL | D71: 100069 | E71: 46014 | F71: entertainment | G71: Payment | H71: credit card | I71: Completed
A72: 10269 | B72: 716 | C72: Active | D72: 100070 | E72: 46024 | G72: Payment | H72: Debit Card | I72: Pending
A73: 10269 | B73: 716 | C73: Active | D73: 100070 | E73: 46024 | G73: Payment | H73: Debit Card | I73: Pending
A74: 10385 | B74: 679 | C74: Active | D74: 100071 | E74: 45451 | F74: Health Care | G74: Payment | H74: Debit | I74: Completed
A75: 10385 | B75: 679 | C75: Active | D75: 100072 | E75: 46220 | F75: rent | G75: Payment | H75: Check | I75: Completed
A76: 10328 | B76: 620 | C76: Active | D76: 100073 | E76: 45016 | F76: DINING | G76: Withdrawal | H76: cash | I76: Completed
A77: 10674 | B77: 633 | C77: Active | D77: 100074 | E77: 45220 | F77: ENTERTAINMENT | G77: Payment | H77: ACH | I77: Completed
A78: NULL | B78: NULL | C78: NULL | D78: 100075 | E78: 45302 | F78: Shopping | G78: Withdrawal | H78: Debit | I78: Completed
A79: 10296 | B79: 471 | C79: Active | D79: 100076 | E79: 45681 | F79: Fee | G79: Fee | H79: ACH | I79: Completed
A80: 10102 | B80: 344 | C80: Closed | D80: 100077 | E80: 45455 | F80: Rent Payment | G80: Payment | H80: CHECK | I80: Completed
A81: 10102 | B81: 344 | C81: Closed | D81: 100077 | E81: 45455 | F81: Rent Payment | G81: Payment | H81: CHECK | I81: Completed
A82: 10627 | B82: 569 | C82: Active | D82: 100078 | E82: 44900 | F82: HEALTHCARE | G82: Payment | H82: check | I82: Completed
A83: 10627 | B83: 569 | C83: Active | D83: 100078 | E83: 44900 | F83: HEALTHCARE | G83: Payment | H83: check | I83: Completed
A84: NULL | B84: NULL | C84: NULL | D84: 100079 | E84: 45168 | F84: SHOPPING | G84: Payment | H84: debit card | I84: Completed
A85: 10416 | B85: 732 | C85: Active | D85: 100080 | E85: 44992 | F85: Insurance | G85: Payment | H85: CREDIT CARD | I85: Completed
A86: 10110 | B86: 445 | C86: Frozen | D86: 100081 | E86: 45134 | F86: Utilities | G86: Payment | H86: CHECK | I86: Completed
A87: 10178 | B87: 497 | C87: Active | D87: 100082 | E87: 46049 | F87: transportation | G87: Payment | H87: Debit | I87: Completed
A88: 10319 | B88: 554 | C88: Closed | D88: 100083 | E88: 44946 | F88: Rent | G88: Payment | H88: Cheque | I88: Pending
A89: NULL | B89: NULL | C89: NULL | D89: 100084 | E89: 45999 | F89: groceries | G89: Withdrawal | H89: credit card | I89: Pending
A90: 10150 | B90: 478 | C90: Active | D90: 100085 | E90: 46232 | F90: Utility | G90: Payment | H90: debit card | I90: Completed
A91: 10264 | B91: 306 | C91: Active | D91: 100086 | E91: 44611 | F91: ENTERTAINMENT | G91: Payment | H91: DEBIT CARD | I91: Completed
A92: 10229 | B92: 416 | C92: Closed | D92: 100087 | E92: 44718 | F92: Fees | G92: Fee | H92: ACH | I92: Completed
A93: 10478 | B93: 306 | C93: Active | D93: 100088 | E93: 45584 | F93: TRANSFER | G93: Transfer | H93: ACH | I93: Completed
A94: 10545 | B94: 400 | C94: Active | D94: 100089 | E94: 44747 | F94: dining | G94: Payment | H94: CREDIT CARD | I94: Completed
A95: 10254 | B95: 361 | C95: Active | D95: 100090 | E95: 45570 | F95: Insurance | G95: Payment | H95: ach | I95: Completed
A96: 10360 | B96: 814 | C96: Active | D96: 100091 | E96: 44684 | F96: dining | G96: Payment | H96: credit card | I96: Completed
A97: NULL | B97: NULL | C97: NULL | D97: 100092 | E97: 45431 | F97: Dining | G97: Withdrawal | H97: credit card | I97: Completed
A98: 10272 | B98: 527 | C98: Active | D98: 100093 | E98: 45175 | F98: Health Care | G98: Payment | I98: Completed
A99: 10440 | B99: 397 | C99: Active | D99: 100094 | E99: 45733 | F99: INSURANCE | G99: Payment | H99: check | I99: Completed
A100: 10266 | B100: 832 | C100: Closed | D100: 100095 | E100: 45980 | F100: Health Care | G100: Payment | H100: Cash | I100: Completed
...

Sheet finance_joined_tables (2)
A1: account_id | B1: credit_score | C1: account_status | D1: transaction_id | E1: transaction_date | F1: category | G1: transaction_type | H1: payment_method | I1: status
A2: NULL | B2: NULL | C2: NULL | D2: 100001 | E2: 44700 | F2: =PROPER(finance_joined_tables!F2) -> Fees | G2: Fee | H2: ACH | I2: Completed
A3: 10357 | B3: 734 | C3: Active | D3: 100002 | E3: 45670 | F3: =PROPER(finance_joined_tables!F3) -> Utilities | G3: Payment | H3: =PROPER(finance_joined_tables!H3) -> Credit Card | I3: Completed
A4: 10140 | B4: 600 | C4: Active | D4: 100003 | E4: 45873 | F4: Entertainment | G4: Payment | H4: ACH | I4: Completed
A5: 10049 | B5: 765 | C5: Active | D5: 100004 | E5: 28/03/2022 | F5: =PROPER(finance_joined_tables!F5) -> Healthcare | G5: Payment | H5: Credit Card | I5: Completed
A6: 10544 | B6: 452 | C6: Closed | D6: 100005 | E6: 44853 | F6: Payroll/Salary | G6: Deposit | H6: ACH | I6: Completed
A7: 10415 | B7: 307 | C7: Active | D7: 100006 | E7: 45949 | F7: =PROPER(finance_joined_tables!F7) -> Utilities | G7: Payment | H7: =PROPER(finance_joined_tables!H7) -> Debit Card | I7: Completed
A8: 10481 | B8: 331 | C8: Active | D8: 100007 | E8: 25/09/2022 | F8: =PROPER(finance_joined_tables!F8) -> Entertainment | G8: Payment | H8: Debit Card | I8: Failed
A9: 10519 | B9: 363 | C9: Active | D9: 100008 | E9: 44820 | F9: =PROPER(finance_joined_tables!F9) -> Insurance | G9: Payment | H9: =PROPER(finance_joined_tables!H9) -> Credit Card | I9: Completed
A10: 10560 | B10: 602 | C10: Active | D10: 100009 | E10: 45327 | F10: =PROPER(finance_joined_tables!F10) -> Insurance | G10: Payment | H10: =PROPER(finance_joined_tables!H10) -> Check | I10: Completed
A11: 10328 | B11: 620 | C11: Active | D11: 100010 | E11: 44883 | F11: =PROPER(finance_joined_tables!F11) -> Dining | G11: Withdrawal | H11: =PROPER(finance_joined_tables!H11) -> Debit Card | I11: Completed
A12: 10636 | B12: 756 | C12: Active | D12: 100011 | E12: 44929 | F12: Healthcare | G12: Payment | H12: =PROPER(finance_joined_tables!H12) -> Check | I12: Completed
A13: 10437 | B13: 335 | C13: Active | D13: 100012 | E13: 45088 | F13: Payroll/Salary | G13: Deposit | H13: ACH | I13: Completed
A14: NULL | B14: NULL | C14: NULL | D14: 100013 | E14: 15/11/2024 | F14: =PROPER(finance_joined_tables!F14) -> Utilities | G14: Payment | H14: Debit Card | I14: Completed
A15: 10385 | B15: 679 | C15: Active | D15: 100014 | E15: 45080 | F15: =PROPER(finance_joined_tables!F15) -> Healthcare | G15: Payment | H15: =PROPER(finance_joined_tables!H15) -> Credit Card | I15: Completed
A16: 10168 | B16: 319 | C16: Active | D16: 100015 | E16: 44609 | F16: =PROPER(finance_joined_tables!F16) -> Fees | G16: Fee | H16: ACH | I16: Failed
A17: 10447 | B17: 387 | C17: Active | D17: 100016 | E17: 45694 | F17: =PROPER(finance_joined_tables!F17) -> Utilities | G17: Payment | H17: =PROPER(finance_joined_tables!H17) -> Debit Card | I17: Completed
A18: 10624 | B18: 640 | C18: Active | D18: 100017 | E18: 45362 | F18: =PROPER(finance_joined_tables!F18) -> Utilities | G18: Payment | H18: =PROPER(finance_joined_tables!H18) -> Check | I18: Completed
A19: 10231 | B19: 419 | C19: Active | D19: 100018 | E19: 26/10/2024 | F19: =PROPER(finance_joined_tables!F19) -> Shopping | G19: Payment | H19: =PROPER(finance_joined_tables!H19) -> Debit Card | I19: Completed
A20: 10249 | B20: 659 | C20: Active | D20: 100019 | E20: 45496 | F20: =PROPER(finance_joined_tables!F20) -> Dining | G20: Withdrawal | H20: =PROPER(finance_joined_tables!H20) -> Credit Card | I20: Completed
A21: 10459 | B21: 682 | C21: Active | D21: 100020 | E21: 45122 | F21: Transfers | G21: Transfer | H21: ACH | I21: Completed
A22: 10334 | B22: 780 | C22: Closed | D22: 100021 | E22: 44616 | F22: Rent | G22: Payment | H22: =PROPER(finance_joined_tables!H22) -> Wire Transfer | I22: Completed
A23: 10061 | B23: 837 | C23: Frozen | D23: 100022 | E23: 46023 | F23: =PROPER(finance_joined_tables!F23) -> Healthcare | G23: Payment | H23: =PROPER(finance_joined_tables!H23) -> Credit Card | I23: Completed
A24: NULL | B24: NULL | C24: NULL | D24: 100023 | E24: 44876 | F24: =PROPER(finance_joined_tables!F24) -> Healthcare | G24: Payment | H24: =PROPER(finance_joined_tables!H24) -> Debit Card | I24: Completed
A25: 10648 | B25: 319 | C25: Active | D25: 100024 | E25: 46133 | F25: Entertainment | G25: Payment | H25: =PROPER(finance_joined_tables!H25) -> Credit Card | I25: Completed
A26: 10375 | B26: 826 | C26: Active | D26: 100025 | E26: 45413 | F26: =PROPER(finance_joined_tables!F26) -> Insurance | G26: Payment | H26: =PROPER(finance_joined_tables!H26) -> Credit Card | I26: Completed
A27: 10402 | B27: 710 | C27: Active | D27: 100026 | E27: 45012 | F27: =PROPER(finance_joined_tables!F27) -> Rent | G27: Payment | H27: =PROPER(finance_joined_tables!H27) -> Check | I27: Completed
A28: 10065 | B28: 753 | C28: Active | D28: 100027 | E28: 45988 | F28: Transportation | G28: Withdrawal | H28: =PROPER(finance_joined_tables!H28) -> Cash | I28: Completed
A29: 10458 | B29: 573 | C29: Active | D29: 100028 | E29: 44589 | F29: =PROPER(finance_joined_tables!F29) -> Entertainment | G29: Payment | H29: Credit Card | I29: Completed
A30: 10648 | B30: 319 | C30: Active | D30: 100029 | E30: 45235 | F30: Utilities | G30: Payment | H30: =PROPER(finance_joined_tables!H30) -> Check | I30: Completed
A31: 10513 | B31: 568 | C31: Closed | D31: 100030 | E31: 45343 | F31: =PROPER(finance_joined_tables!F31) -> Insurance | G31: Payment | H31: =PROPER(finance_joined_tables!H31) -> Credit Card | I31: Completed
A32: 10271 | B32: 714 | C32: Active | D32: 100031 | E32: 46046 | F32: =PROPER(finance_joined_tables!F32) -> Healthcare | G32: Payment | H32: Credit Card | I32: Completed
A33: 10293 | B33: 696 | C33: Closed | D33: 100032 | E33: 22/06/2024 | F33: =PROPER(finance_joined_tables!F33) -> Transportation | G33: Withdrawal | H33: =PROPER(finance_joined_tables!H33) -> Credit Card | I33: Completed
A34: NULL | B34: NULL | C34: NULL | D34: 100033 | E34: 45330 | F34: =PROPER(finance_joined_tables!F34) -> Insurance | G34: Payment | H34: =PROPER(finance_joined_tables!H34) -> Check | I34: Completed
A35: 10178 | B35: 497 | C35: Active | D35: 100034 | E35: 45564 | F35: Payroll/Salary | G35: Deposit | H35: ACH | I35: Pending
A36: 10436 | B36: 631 | C36: Active | D36: 100035 | E36: 45430 | F36: =PROPER(finance_joined_tables!F36) -> Shopping | G36: Withdrawal | H36: =PROPER(finance_joined_tables!H36) -> Debit Card | I36: Completed
A37: NULL | B37: NULL | C37: NULL | D37: 100036 | E37: 46140 | F37: Rent | G37: Payment | H37: Wire Transfer | I37: Completed
A38: 10471 | B38: 448 | C38: Active | D38: 100037 | E38: 44744 | F38: =PROPER(finance_joined_tables!F38) -> Rent | G38: Payment | H38: =PROPER(finance_joined_tables!H38) | I38: Pending
A39: NULL | B39: NULL | C39: NULL | D39: 100038 | E39: 45444 | F39: Utilities | G39: Payment | H39: =PROPER(finance_joined_tables!H39) -> Debit Card | I39: Completed
A40: 10468 | B40: 756 | C40: Active | D40: 100039 | E40: 45399 | F40: =PROPER(finance_joined_tables!F40) -> Healthcare | G40: Payment | H40: =PROPER(finance_joined_tables!H40) -> Check | I40: Completed
A41: 10260 | B41: 312 | C41: Active | D41: 100040 | E41: 44647 | F41: =PROPER(finance_joined_tables!F41) -> Rent | G41: Payment | H41: Wire Transfer | I41: Pending
A42: 10042 | B42: 555 | C42: Active | D42: 100041 | E42: 44679 | F42: =PROPER(finance_joined_tables!F42) -> Dining | G42: Withdrawal | H42: Credit Card | I42: Completed
A43: 10436 | B43: 631 | C43: Active | D43: 100042 | E43: 31/08/2024 | F43: =PROPER(finance_joined_tables!F43) -> Insurance | G43: Payment | H43: ACH | I43: Completed
A44: 10698 | B44: 427 | C44: Active | D44: 100043 | E44: 45331 | F44: Transfers | G44: Transfer | H44: Wire Transfer | I44: Completed
A45: 10463 | B45: 611 | C45: Active | D45: 100044 | E45: 45518 | F45: =PROPER(finance_joined_tables!F45) -> Utilities | G45: Payment | H45: =PROPER(finance_joined_tables!H45) -> Debit Card | I45: Completed
A46: NULL | B46: NULL | C46: NULL | D46: 100045 | E46: 45537 | F46: Transfers | G46: Transfer | H46: ACH | I46: Completed
A47: 10416 | B47: 732 | C47: Active | D47: 100046 | E47: 45456 | F47: Entertainment | G47: Payment | H47: =PROPER(finance_joined_tables!H47) -> Debit Card | I47: Completed
A48: 10077 | B48: 448 | C48: Closed | D48: 100047 | E48: 45770 | F48: =PROPER(finance_joined_tables!F48) -> Insurance | G48: Payment | H48: =PROPER(finance_joined_tables!H48) -> Check
A49: 10402 | B49: 710 | C49: Active | D49: 100048 | E49: 45010 | F49: =PROPER(finance_joined_tables!F49) -> Healthcare | G49: Payment | H49: =PROPER(finance_joined_tables!H49) -> Credit Card | I49: Completed
A50: 10197 | B50: 315 | C50: Active | D50: 100049 | E50: 18/07/2026 | F50: =PROPER(finance_joined_tables!F50) -> Dining | G50: Withdrawal | H50: =PROPER(finance_joined_tables!H50) -> Cash | I50: Completed
A51: 10363 | B51: 722 | C51: Closed | D51: 100050 | E51: 45950 | F51: =PROPER(finance_joined_tables!F51) -> Healthcare | G51: Payment | H51: =PROPER(finance_joined_tables!H51) -> Debit Card | I51: Completed
A52: 10447 | B52: 387 | C52: Active | D52: 100051 | E52: 44843 | F52: Healthcare | G52: Payment | H52: =PROPER(finance_joined_tables!H52) -> Credit Card | I52: Completed
A53: 10545 | B53: 400 | C53: Active | D53: 100052 | E53: 44677 | F53: Rent | G53: Payment | H53: =PROPER(finance_joined_tables!H53) -> Check | I53: Failed
A54: 10269 | B54: 716 | C54: Active | D54: 100053 | E54: 44915 | F54: =PROPER(finance_joined_tables!F54) -> Transfers | G54: Transfer | H54: =PROPER(finance_joined_tables!H54) -> Wire Transfer | I54: Completed
A55: 10100 | B55: 448 | C55: Active | D55: 100054 | E55: 45544 | F55: =PROPER(finance_joined_tables!F55) -> Transfers | G55: Deposit | H55: =PROPER(finance_joined_tables!H55) -> Wire Transfer | I55: Completed
A56: 10227 | B56: 773 | C56: Active | D56: 100055 | E56: 46225 | F56: Payroll/Salary | G56: Payment | H56: ACH | I56: Completed
A57: 10361 | B57: 460 | C57: Active | D57: 100056 | E57: 46104 | F57: =PROPER(finance_joined_tables!F57) -> Insurance | G57: Payment | H57: ACH | I57: Completed
A58: 10207 | B58: 516 | C58: Active | D58: 100057 | E58: 45202 | F58: =PROPER(finance_joined_tables!F58) -> Groceries | G58: Payment | H58: =PROPER(finance_joined_tables!H58) -> Credit Card | I58: Completed
A59: 10333 | B59: 554 | C59: Active | D59: 100058 | E59: 45836 | F59: =PROPER(finance_joined_tables!F59) -> Insurance | G59: Payment | H59: =PROPER(finance_joined_tables!H59) -> Credit Card | I59: Completed
A60: 10525 | B60: 409 | C60: Active | D60: 100059 | E60: 45324 | F60: Transportation | G60: Fee | H60: =PROPER(finance_joined_tables!H60) -> Credit Card | I60: Completed
A61: 10572 | B61: 498 | C61: Active | D61: 100060 | E61: 14/07/2023 | F61: =PROPER(finance_joined_tables!F61) -> Fees | G61: Payment | H61: ACH | I61: Failed
A62: 10035 | B62: 345 | C62: Active | D62: 100061 | E62: 17/03/2025 | F62: Utilities | G62: Deposit | H62: ACH | I62: Pending
A63: 10505 | B63: 381 | C63: Active | D63: 100062 | E63: 45968 | F63: Payroll/Salary | G63: Payment | H63: ACH | I63: Completed
A64: 10060 | B64: 613 | C64: Active | D64: 100063 | E64: 19/07/2023 | F64: =PROPER(finance_joined_tables!F64) -> Insurance | G64: Payment | H64: ACH | I64: Pending
A65: 10141 | B65: 665 | C65: Active | D65: 100064 | E65: 45571 | F65: =PROPER(finance_joined_tables!F65) -> Transportation | G65: Withdrawal | H65: =PROPER(finance_joined_tables!H65) -> Cash | I65: Completed
A66: NULL | B66: NULL | C66: NULL | D66: 100065 | E66: 46000 | F66: =PROPER(finance_joined_tables!F66) | G66: Payment | H66: Credit Card | I66: Completed
A67: NULL | B67: NULL | C67: NULL | D67: 100066 | E67: 44793 | F67: =PROPER(finance_joined_tables!F67) -> Insurance | G67: Payment | H67: =PROPER(finance_joined_tables!H67) -> Credit Card | I67: Completed
A68: 10597 | B68: 800 | C68: Active | D68: 100067 | E68: 45561 | F68: =PROPER(finance_joined_tables!F68) -> Dining | G68: Payment | H68: Credit Card | I68: Completed
A69: 10515 | B69: 499 | C69: Active | D69: 100068 | E69: 44576 | F69: =PROPER(finance_joined_tables!F69) -> Groceries | G69: Payment | H69: =PROPER(finance_joined_tables!H69) -> Credit Card | I69: Completed
A70: NULL | B70: NULL | C70: NULL | D70: 100069 | E70: 46014 | F70: =PROPER(finance_joined_tables!F70) -> Utilities | G70: Payment | H70: =PROPER(finance_joined_tables!H70) -> Check | I70: Completed
A71: 10269 | B71: 716 | C71: Active | D71: 100070 | E71: 46024 | F71: =PROPER(finance_joined_tables!F71) -> Entertainment | G71: Payment | H71: =PROPER(finance_joined_tables!H71) -> Credit Card | I71: Pending
A72: 10385 | B72: 679 | C72: Active | D72: 100071 | E72: 45451 | F72: =PROPER(finance_joined_tables!F72) | G72: Payment | H72: =PROPER(finance_joined_tables!H72) -> Debit Card | I72: Completed
A73: 10385 | B73: 679 | C73: Active | D73: 100072 | E73: 46220 | F73: =PROPER(finance_joined_tables!F73) | G73: Payment | H73: =PROPER(finance_joined_tables!H73) -> Debit Card | I73: Completed
A74: 10328 | B74: 620 | C74: Active | D74: 100073 | E74: 45016 | F74: Healthcare | G74: Withdrawal | H74: Debit Card | I74: Completed
A75: 10674 | B75: 633 | C75: Active | D75: 100074 | E75: 45220 | F75: =PROPER(finance_joined_tables!F75) -> Rent | G75: Payment | H75: =PROPER(finance_joined_tables!H75) -> Check | I75: Completed
A76: NULL | B76: NULL | C76: NULL | D76: 100075 | E76: 45302 | F76: =PROPER(finance_joined_tables!F76) -> Dining | G76: Withdrawal | H76: =PROPER(finance_joined_tables!H76) -> Cash | I76: Completed
A77: 10296 | B77: 471 | C77: Active | D77: 100076 | E77: 45681 | F77: =PROPER(finance_joined_tables!F77) -> Entertainment | G77: Fee | H77: ACH | I77: Completed
A78: 10102 | B78: 344 | C78: Closed | D78: 100077 | E78: 45455 | F78: =PROPER(finance_joined_tables!F78) -> Shopping | G78: Payment | H78: Debit Card | I78: Completed
A79: 10627 | B79: 569 | C79: Active | D79: 100078 | E79: 44900 | F79: Fees | G79: Payment | H79: ACH | I79: Completed
A80: NULL | B80: NULL | C80: NULL | D80: 100079 | E80: 45168 | F80: Rent | G80: Payment | H80: =PROPER(finance_joined_tables!H80) -> Check | I80: Completed
A81: 10416 | B81: 732 | C81: Active | D81: 100080 | E81: 44992 | F81: Rent | G81: Payment | H81: =PROPER(finance_joined_tables!H81) -> Check | I81: Completed
A82: 10110 | B82: 445 | C82: Frozen | D82: 100081 | E82: 45134 | F82: =PROPER(finance_joined_tables!F82) -> Healthcare | G82: Payment | H82: =PROPER(finance_joined_tables!H82) -> Check | I82: Completed
A83: 10178 | B83: 497 | C83: Active | D83: 100082 | E83: 46049 | F83: =PROPER(finance_joined_tables!F83) -> Healthcare | G83: Payment | H83: =PROPER(finance_joined_tables!H83) -> Check | I83: Completed
A84: 10319 | B84: 554 | C84: Closed | D84: 100083 | E84: 44946 | F84: =PROPER(finance_joined_tables!F84) -> Shopping | G84: Payment | H84: =PROPER(finance_joined_tables!H84) -> Debit Card | I84: Pending
A85: NULL | B85: NULL | C85: NULL | D85: 100084 | E85: 45999 | F85: =PROPER(finance_joined_tables!F85) -> Insurance | G85: Withdrawal | H85: =PROPER(finance_joined_tables!H85) -> Credit Card | I85: Pending
A86: 10150 | B86: 478 | C86: Active | D86: 100085 | E86: 46232 | F86: =PROPER(finance_joined_tables!F86) -> Utilities | G86: Payment | H86: =PROPER(finance_joined_tables!H86) -> Check | I86: Completed
A87: 10264 | B87: 306 | C87: Active | D87: 100086 | E87: 44611 | F87: =PROPER(finance_joined_tables!F87) -> Transportation | G87: Payment | H87: Debit Card | I87: Completed
A88: 10229 | B88: 416 | C88: Closed | D88: 100087 | E88: 44718 | F88: =PROPER(finance_joined_tables!F88) -> Rent | G88: Fee | H88: Check | I88: Completed
A89: 10478 | B89: 306 | C89: Active | D89: 100088 | E89: 45584 | F89: =PROPER(finance_joined_tables!F89) -> Groceries | G89: Transfer | H89: =PROPER(finance_joined_tables!H89) -> Credit Card | I89: Completed
A90: 10545 | B90: 400 | C90: Active | D90: 100089 | E90: 44747 | F90: Utilities | G90: Payment | H90: =PROPER(finance_joined_tables!H90) -> Debit Card | I90: Completed
A91: 10254 | B91: 361 | C91: Active | D91: 100090 | E91: 45570 | F91: =PROPER(finance_joined_tables!F91) -> Entertainment | G91: Payment | H91: =PROPER(finance_joined_tables!H91) -> Debit Card | I91: Completed
A92: 10360 | B92: 814 | C92: Active | D92: 100091 | E92: 44684 | F92: =PROPER(finance_joined_tables!F92) -> Fees | G92: Payment | H92: ACH | I92: Completed
A93: NULL | B93: NULL | C93: NULL | D93: 100092 | E93: 45431 | F93: Transfers | G93: Withdrawal | H93: ACH | I93: Completed
A94: 10272 | B94: 527 | C94: Active | D94: 100093 | E94: 45175 | F94: =PROPER(finance_joined_tables!F94) -> Dining | G94: Payment | H94: =PROPER(finance_joined_tables!H94) -> Credit Card | I94: Completed
A95: 10440 | B95: 397 | C95: Active | D95: 100094 | E95: 45733 | F95: =PROPER(finance_joined_tables!F95) -> Insurance | G95: Payment | H95: ACH | I95: Completed
A96: 10266 | B96: 832 | C96: Closed | D96: 100095 | E96: 45980 | F96: =PROPER(finance_joined_tables!F96) -> Dining | G96: Payment | H96: =PROPER(finance_joined_tables!H96) -> Credit Card | I96: Completed
A97: 10221 | B97: 337 | C97: Active | D97: 100096 | E97: 44695 | F97: =PROPER(finance_joined_tables!F97) -> Dining | G97: Payment | H97: =PROPER(finance_joined_tables!H97) -> Credit Card | I97: Completed
A98: 10032 | B98: 504 | C98: Active | D98: 100097 | E98: 45292 | F98: Healthcare | G98: Deposit | H98: =PROPER(finance_joined_tables!H98) | I98: Failed
A99: NULL | B99: NULL | C99: NULL | D99: 100098 | E99: 18/03/2022 | F99: =PROPER(finance_joined_tables!F99) -> Insurance | G99: Deposit | H99: =PROPER(finance_joined_tables!H99) -> Check | I99: Pending
A100: 10101 | B100: 478 | C100: Active | D100: 100099 | E100: 45261 | F100: Healthcare | G100: Payment | H100: =PROPER(finance_joined_tables!H100) -> Cash | I100: Completed
...
